Workbook
Name Spinne1: Analyse!$C$4

Sheet Instructions
A1: Instructions relatives au questionnaire «Autoévaluation»
A2: Introduction Vous avez décidé de renforcer de manière systématique la sécurité au travail et la protection de la santé au sein de votre entreprise par le biais du projet «Sécurité intégrée». Dans cette optique, ce questionnaire constitue un outil essentiel. Il vous permet de contrôler l’état actuel de la sécurité au travail et de la protection de la santé au niveau interne et de collecter les informations nécessaires à la réalisation du projet. Les remarques ci-après doivent vous aider à remplir le questionnaire.
A3: 1. Structure du questionnaire - Tableaux - Informations concernant l’entreprise - Personnes clés pour la sécurité au travail - Autoévaluation client - Aperçu des annexes (à titre informatif)
A4: 2. Structure des différents tableaux - Seules les cellules à compléter sont déverrouillées. - Les plages des cellules à remplir sont grisées. - Les autres plages déverrouillées peuvent être remplies au cas par cas. - La touche de tabulation permet de passer rapidement d’un champ déverrouillé au suivant.
A5: 3. Tableau «Informations concernant l’entreprise» - Complétez la colonne «Saisie client» avec les informations demandées.
A6: 4. Tableur «Personnes clés pour la sécurité au travail» - Complétez la colonne «Fonction/Compétence» avec les fonctions existantes au sein de l’entreprise. - Remplissez la colonne «Nom/Prénom» pour toutes les «Fonctions/Compétences» mentionnées qui existent au sein de l’entreprise.
A7: 5. Tableau «Autoévaluation client» - Répondez à toutes les questions par «Oui» ou par «Non» en insérant le symbole «x» dans le champ correspondant. - Vous pouvez ajouter un commentaire dans la colonne «Remarque client» prévue à cet effet. - En fonction de votre réponse à certaines questions, un commentaire peut être obligatoire (dans ce cas, la colonne «Remarque client» est grisée). - Certaines questions sont en plusieurs parties. - Dans ce cas, la question principale est affichée sur fond bleu.
A8: 6. Annexes - Certaines questions du tableau «Autoévaluation client» nécessitent impérativement une annexe à des fins de documentation (si disponible). - Le numéro de l’annexe en question est indiqué dans la colonne «Annexe nécessaire». - Tous les numéros des annexes sont indiqués dans le tableau «Aperçu des annexes». - Des annexes supplémentaires peuvent être jointes en cas de besoin. - Merci de bien vouloir nous transmettre les annexes si possible au format pdf.
A9: FO.250.f.V14

Sheet Fiche signalétique
A1: Fiche signalétique de l'entreprise
C2: Saisie client :
A3: 1. Nom de l'entreprise | C3: Exemple SA
A4: 2. Siège social
A5: 3. Date de création
A6: 4. Sites
A7: 5. Forme juridique
A8: 6. Propriétaires
A9: 7. Organes
A10: 8. Produits
A11: 9. Clientèle
A12: 10. Certificats environnementaux et de qualité
A13: 11. Documents de l'entreprise
A14: 12. Unités organisationnelles de l'entreprise et nombre d'employés dans chaque Unité organisationnelle
A15: 13. Etendue des responsabilités* dans votre entreprise *Etendue des responsabilités = nombre de collaborateurs directement subordonnés à un supérieur hiérarchique | B15: au niveau des cadres supérieurs
B16: au niveau des cadres moyens
B17: au niveau des cadres inférieurs
A18: 14. Nombre d'employés | B18: Direction
B19: Cadres
B20: Collaborateurs
B21: Apprentis
B22: Total collaborateurs
A23: 15. Evolution tendancielle Nombre d'employés (en hausse / constant / en diminution) | B23: Membres des cadres
B24: Collaborateurs
B25: Apprentis
B26: Total
A27: 16. Statut de formation des employés (en %) | B27: Diplôme universitaire
B28: Formation profes-sionnelle supérieure (HES/ETS/ET)
B29: Formation professionnelle
B30: Formation élémentaire
A31: 17. Nationalités des employés
A32: 18. Langues maternelles des employés
A33: 19. Dangers spécifiques à l'exploitation

Sheet Interlocuteurs sécurité
A1: Interlocuteurs de la sécurité au travail
A2: Fonction / compétences | B2: Nom / prénom
A3: Direction
A14: Chef de division (pour autant que la réponse ne figure pas dans l'organigramme annexé)
A26: Direction et team de projet IS
A37: Organisation de la sécurité
A38: Coordinateur de la sécurité
A39: Ingénieur de sécurité
A40: Chargé de sécurité
A41: Assistant de sécurité
A42: Coordinateur de l'ergonomie
A43: Personne de contact pour les produits chimiques
A44: Responsable de la radioprotection
A45: Spécialistes MSST
... A121: Autres employés clés (à remplir si nécessaire)

Sheet Autoévaluation client
A1: Autoévaluation par le client
A2: N° | C2: Description question | D2: Oui | E2: Non | F2: Remarque du client | G2: Annexe requise
A3: 1. | B3: Ligne de conduite, objectifs et stratégie
B4: Visa gestionnaire du dossier Chapitre 1:
A5: 1.1. | B5: Ligne de conduite de l'entreprise, principes directeurs
A6: 1.1.1. | C6: L'entreprise dispose-t-elle d'une charte d'entreprise? | G6: 1.A
A7: 1.1.2. | C7: La sécurité et la santé du personnel font-elles partie de la charte d'entreprise?
A8: 1.1.3. | C8: Les collobrateurs sont-ils informés de la philosophie et des conséquences pratiques de la charte d'entreprise?
A9: 1.1.4. | C9: Le reflet de la situation dans l'entreprise correspond-il à la charte d'entreprise?
A10: 1.1.5. | C10: Le comportement des supérieurs dans votre entreprise est-il déterminé par des principes ou des directives de conduite spécifiques? Si oui, lesquels?
A11: 1.1.6. | C11: La sécurité et la protection de la santé sont-elle expressément intégrées dans les principes ou les directives de conduite? | G11: 1.B
A12: 1.1.7. | C12: Est-ce que la société a signé la Charte de sécurité de la Suva?
A13: 1.1.8.a | C13: L'un des systèmes de management / certifications suivants est-il en vigueur: ISO 9001, ISO 14001, ISO 45001, OHSAS18001 ? Si oui, lequel?
A14: 1.1.8.b | C14: Un autre système de management / certifications est-il en vigueur? Si oui, lequel?
A15: 1.2. | B15: Engagement de la direction
A16: 1.2.1. | C16: La direction de l'entreprise montre-t-elle l'exemple à suivre en matière de sécurité et de santé à l'aide d'exigences, de décisions, de règles et d'instructions concrètes?
A17: 1.2.2. | C17: Votre entreprise accorde-t-elle à la sécurité au travail la même valeur qu'à la qualité et à la productivité?
A18: 1.2.3. | C18: La direction aborde-t-elle les situations et les comportements à risque lors de ses inspections dans les entreprises?
A19: 1.2.4. | C19: Le budget prévoit-il des ressources pour la sécurité au travail et la protection de la santé?
A20: 1.2.5.a | C20: La direction soutient-elle dans l'entreprise... les évaluations du risque?
A21: 1.2.5.b | C21: les audits, les contrôles?
A22: 1.2.5.c | C22: les analyses d'accidents?
A23: 1.2.5.d | C23: la formation des collaborateurs sur le lieu de travail?
A24: 1.2.5.e | C24: la mise en œuvre de mesures adéquates?
A25: 1.2.5.f | C25: les campagnes en faveur de la sécurité au travail?
A26: 1.2.5.g | C26: les campagnes en faveur de la sécurité durant les loisirs?
A27: 1.2.5.h | C27: la gestion des absences?
A28: 1.2.5.i | C28: autres? Si oui, lesquels?
A29: 1.3. | B29: Engagement des supérieurs hiérarchiques
A30: 1.3.1.a | C30: Les supérieurs hiérarchiques promeuvent-ils la sécurité et la santé : en se conformant aux prescriptions de sécurité (par ex. le port de l'équipement de protection individuelle (EPI))?
A31: 1.3.1.b | C31: en faisant respecter l'observation des prescriptions de sécurité?
A32: 1.3.1.c | C32: par d'autres formes d'incitations? Si oui, lesquelles?
A33: 1.3.2.a | C33: Les supérieurs hiérarchiques de l'entreprise s'engagent-ils pour la sécurité et la santé des employés, en réalisant... des évaluations de risque?
A34: 1.3.2.b | C34: des audits, des contrôles?
A35: 1.3.2.c | C35: des analyses d'accidents?
A36: 1.3.2.d | C36: de la formation des collaborateurs à la place de travail?
A37: 1.3.2.e | C37: des campagnes en faveur de la sécurité au travail?
A38: 1.3.2.f | C38: des campagnes en faveur de la sécurité durant les loisirs?
A39: 1.3.2.g | C39: la gestion des absences?
A40: 1.3.2.h | C40: d'autres actions? Si oui, lesquelles?
A41: 1.3.3 | C41: Les supérieurs hiérarchiques connaissent-ils les droits et les obligations résultant des exigences légales en matière de sécurité et de santé?
A42: 1.4. | B42: Objectifs de sécurité
A43: 1.4.1.a | C43: Existe-t-il des objectifs mesurables concernant la limitation de la fréquence* des événements suivants: * Fréquence = nombre d'événements par rapport au temps de travail productif ou nombre d'événements par rapport au nombre de salariés à plein temps durant une période donnée. Accidents professionnels / maladies professionnels? | G43: 1.C
A44: 1.4.1.b | C44: Accidents non professionnels?
A45: 1.4.1.c | C45: Maladies?
A46: 1.4.1.d | C46: Dommages matériels?
A47: 1.4.1.e | C47: Perturbations?
A48: 1.4.1.f | C48: Autres événements? Si oui, lesquels?
A49: 1.4.2.a | C49: Existe-t-il des objectifs mesurables visant à restreindre la durée des absences consécutives à... des accidents professionnels / maladies professionnels?
A50: 1.4.2.b | C50: des accidents non professionnels?
A51: 1.4.2.c | C51: des maladies?
A52: 1.4.2.d | C52: d'autres événements? Si oui, lesquels?
A53: 1.4.3. | C53: Vos objectifs en matière de sécurité et de santé s'appliquent-ils à l'entreprise dans son ensemble?
A54: 1.4.4. | C54: Vos objectifs en matière de sécurité et de santé s'appliquent-ils à des unités d'organisation spécifiques?
A55: 1.4.5. | C55: Avez-vous la possibilité de comparer les résultats avec des entreprises similaires (même branche)? Si oui, lesquelles?
A56: 1.5. | B56: Elaboration et contrôle des objectifs, stratégie
A57: 1.5.1. | C57: Un processus est-il défini pour l'élaboration des objectifs de sécurité?
A58: 1.5.2. | C58: Un engagement pour l'amélioration continue du système de sécurité est-elle contenue dans les objectifs?
A59: 1.5.3. | C59: Les cadres, ou leur représentants, participent-ils à l'élaboration des objectifs de sécurité?
A60: 1.5.4. | C60: Les écarts par rapport aux objectifs sont-ils constatés à temps par le biais d'un relevé des événements (ou d'une évaluation intermédiaire des objectifs en cours d'année) s'appliquant à l'entreprise dans son ensemble?
A61: 1.5.5. | C61: Les écarts par rapport aux objectifs sont-ils constatés à temps par le biais d'un relevé des événements (ou d'une évaluation intermédiaire des objectifs en cours d'année) s'appliquant à des unités d'organisation spécifiques (secteur, division)?
A62: 1.5.6. | C62: Lorsque les objectifs ne sont pas atteints, en tirez-vous les conséquences et prenez-vous les mesures correctrices nécessaires? Si oui, lesquelles?
A63: 1.5.7. | C63: Disposez-vous d'une stratégie de sécurité qui vous aide à atteindre vos objectifs de sécurité (p. ex. paquets de mesures prévus à moyen terme, futures tendances, exigences et attentes des parties intéressées) ? Si oui, laquelle?
A65: 2. | B65: Organisation
B66: Visa gestionnaire du dossier Chapitre 2:
A67: 2.1. | B67: Organisation de l'entreprise
A68: 2.1.1 | C68: Type d'organisation
A69: 2.1.1.1.a | C69: Quel type d’organisation structurelle existe dans votre entreprise: Organisation hiérarchique? | G69: 2.A
A70: 2.1.1.2.b | C70: Organisation d’état-major de ligne?
A71: 2.1.1.2.c | C71: Organisation fonctionnelle?
A72: 2.1.1.2.d | C72: Organisation matricielle?
A73: 2.1.1.2.e | C73: Organisation de projets?
A74: 2.1.1.2.f | C74: Autre forme? Si oui, laquelle?
A75: 2.1.2. | C75: Tâches, compétences, responsabilités
A76: 2.1.2.1. | C76: Les compétences et les responsabilités concernant la sécurité et la santé des collaborateurs sont-elles définies par écrit?
A77: 2.1.2.2.a | C77: Votre entreprise dispose-t-elle de documents d'organisation tels que: Descriptions des postes de travail? | G77: 2.B, 2.C, 2.D
A78: 2.1.2.2.b | C78: Cahiers des charges?
A79: 2.1.2.2.c | C79: Diagrammes fonctionnels
A80: 2.1.2.2.d | C80: Règlements? | G80: 2.E
A81: 2.1.2.2.e | C81: Contrats de travail individuels?
A82: 2.1.2.2.f | C82: Contrats de travail collectifs?
A83: 2.1.2.2.g | C83: Contrats d'entreprise?
A84: 2.1.2.2.h | C84: Autres documents d'organisation? Si oui, lesquels?
A85: 2.1.2.3.a | C85: Les tâches, compétences, responsabilités (obligations et droits) concernant la sécurité et la santé font-elles partie des documents suivants: Descriptions des postes?
A86: 2.1.2.3.b | C86: Cahiers des charges? | G86: 2.F
A87: 2.1.2.3.c | C87: Diagrammes fonctionnels
A88: 2.1.2.3.d | C88: Règlements?
A89: 2.1.2.3.e | C89: Contrats de travail individuels?
A90: 2.1.2.3.f | C90: Contrats de travail collectifs?
A91: 2.1.2.3.g | C91: Contrats d'entreprise?
A92: 2.1.2.3.h | C92: Autres documents d'organisation? Si oui, lesquels?
A93: 2.1.3. | C93: Planification et organisation du travail
A94: 2.1.3.1.a | C94: La planification, le calcul, l'organisation et la préparation des ordres de travail sont-ils effectués par : Les supérieurs hiérarchiques?
A95: 2.1.3.1.b | C95: Des teams de projet?
A96: 2.1.3.1.c | C96: D’une unité organisationnelle spéciale (AVOR / Préparation du travail)?
A97: 2.1.3.1.d | C97: Autres organes/personnes? Si oui, quels organes/personnes?
A98: 2.1.3.2. | C98: Des aspects de la sécurité au travail et de la protection de la santé sont-ils pris en considération au cours des phases de la planification, de l'organisation et de la préparation du travail?
... A103: 2.1.3.7. | C103: Les ordres de travail sont-ils donnés et documentés sous forme écrite ?
A104: 2.1.3.8. | C104: Les instructions de travail écrites font-elles référence à des mesures de sécurité et de protection de la santé? | G104: 2.G
A105: 2.1.4. | C105: Règlement d'entreprise
...

Sheet Annexes
A1: Annexes nécessaires (si disponibles) Veuillez nous envoyer les documents suivants, si possible au format PDF.
A2: Annexes N° | B2: Description
A3: 1.A | B3: La charte des valeurs de l'entreprise
A4: 1.B | B4: Principes / directives de conduite de l'entreprise
A5: 1.C | B5: Définition écrite des objectifs de sécurité de l'entreprise
A6: 2.A | B6: Organigramme de l'entreprise
A7: 2.B | B7: Cahier des charges pour les supérieur
A8: 2.C | B8: Cahier des charges pour tout poste sans responsabilité de gestion
A9: 2.D | B9: Cahier des charges pour le coordinateur de la sécurité
A10: 2.E | B10: Règlement du personnel de l'entreprise
A11: 2.F | B11: Autres documents qui réglementent les tâches, les compétences et les responsabilités concernant la sécurité et la santé
A12: 2.G | B12: Exemple d'une instruction de travail écrite
A13: 2.H | B13: Règlement d'entreprise
... A43: 11.B | B43: Objectifs et chiffres indicateurs sociaux de la gestion des absences

Sheet Analyse
A1: Firma | B1: ='Fiche signalétique'!C3 -> Exemple SA | C1: Datum | E1: Nr.
A2: Analyse und Bewertung für Selbstbeuteilung und Ist-Aufnahme | C2: Antwort Kunde | F2: Interviewpartner | L2: Bewertung Suva | M2: Berechnung für Diagramm
C3: ja/nein (* keine Antwort) | E3: Bemerkungen des Kunden | F3: GL | G3: Führung | H3: HR | I3: Si Org | J3: VG | K3: MA | L3: Erfüllungsgrad in Prozent | M3: Gewicht | N3: max Punktzahl | O3: Punkte Selbst | P3: Punkte Suva | Q3: Level 1 Selbst | R3: Level 1 Suva
A4: 1 | B4: ='Autoévaluation client'!B3 -> Ligne de conduite, objectifs et stratégie | C4: =O4/N4 -> 0 | L4: =P4/N4 -> 0 | N4: =SUM(M5,M15,M29,M42,M56) -> 17 | O4: =SUM(Q5:Q63) -> 0 | P4: =SUM(R5:R63) -> 0
A5: ='Autoévaluation client'!A5 -> 1.1. | B5: ='Autoévaluation client'!B5 -> Ligne de conduite de l'entreprise, principes directeurs | C5: =O5/N5 -> 0 | L5: =P5/N5 -> 0 | M5: 3 | N5: =SUM(M6:M14) -> 25 | O5: =SUM(O6:O14) -> 0 | P5: =SUM(P6:P14) -> 0 | Q5: =O5/$N5*$M5 -> 0 | R5: =P5/$N5*$M5 -> 0
A6: ='Autoévaluation client'!A6 -> 1.1.1. | B6: ='Autoévaluation client'!C6 -> L'entreprise dispose-t-elle d'une charte d'entreprise? | C6: =IF(ISBLANK('Autoévaluation client'!D6),0,1) -> 0 | D6: =IF(AND('Autoévaluation client'!D6="",'Autoévaluation client'!E6=""),"*","") -> * | M6: 3 | O6: =C6*M6 -> 0 | P6: =L6*M6 -> 0
A7: ='Autoévaluation client'!A7 -> 1.1.2. | B7: ='Autoévaluation client'!C7 -> La sécurité et la santé du personnel font-elles partie de la charte d'entreprise? | C7: =IF(ISBLANK('Autoévaluation client'!D7),0,1) -> 0 | D7: =IF(AND('Autoévaluation client'!D7="",'Autoévaluation client'!E7=""),"*","") -> * | E7: =IF(ISBLANK('Autoévaluation client'!F7),"",'Autoévaluation client'!F7) | M7: 4 | O7: =C7*M7 -> 0 | P7: =L7*M7 -> 0
A8: ='Autoévaluation client'!A8 -> 1.1.3. | B8: ='Autoévaluation client'!C8 -> Les collobrateurs sont-ils informés de la philosophie et des conséquences pratiques de la charte d'entreprise? | C8: =IF(ISBLANK('Autoévaluation client'!D8),0,1) -> 0 | D8: =IF(AND('Autoévaluation client'!D8="",'Autoévaluation client'!E8=""),"*","") -> * | E8: =IF(ISBLANK('Autoévaluation client'!F8),"",'Autoévaluation client'!F8) | M8: 5 | O8: =C8*M8 -> 0 | P8: =L8*M8 -> 0
A9: ='Autoévaluation client'!A9 -> 1.1.4. | B9: ='Autoévaluation client'!C9 -> Le reflet de la situation dans l'entreprise correspond-il à la charte d'entreprise? | C9: =IF(ISBLANK('Autoévaluation client'!D9),0,1) -> 0 | D9: =IF(AND('Autoévaluation client'!D9="",'Autoévaluation client'!E9=""),"*","") -> * | E9: =IF(ISBLANK('Autoévaluation client'!F9),"",'Autoévaluation client'!F9) | M9: 5 | O9: =C9*M9 -> 0 | P9: =L9*M9 -> 0
A10: ='Autoévaluation client'!A10 -> 1.1.5. | B10: ='Autoévaluation client'!C10 -> Le comportement des supérieurs dans votre entreprise est-il déterminé par des principes ou des directives de conduite spécifiques? Si oui, lesquels? | C10: =IF(ISBLANK('Autoévaluation client'!D10),0,1) -> 0 | D10: =IF(AND('Autoévaluation client'!D10="",'Autoévaluation client'!E10=""),"*","") -> * | E10: =IF(ISBLANK('Autoévaluation client'!F10),"",'Autoévaluation client'!F10) | M10: 0 | O10: =C10*M10 -> 0 | P10: =L10*M10 -> 0
A11: ='Autoévaluation client'!A11 -> 1.1.6. | B11: ='Autoévaluation client'!C11 -> La sécurité et la protection de la santé sont-elle expressément intégrées dans les principes ou les directives de conduite? | C11: =IF(ISBLANK('Autoévaluation client'!D11),0,1) -> 0 | D11: =IF(AND('Autoévaluation client'!D11="",'Autoévaluation client'!E11=""),"*","") -> * | E11: =IF(ISBLANK('Autoévaluation client'!F11),"",'Autoévaluation client'!F11) | M11: 3 | O11: =C11*M11 -> 0 | P11: =L11*M11 -> 0
A12: ='Autoévaluation client'!A12 -> 1.1.7. | B12: ='Autoévaluation client'!C12 -> Est-ce que la société a signé la Charte de sécurité de la Suva? | C12: =IF(ISBLANK('Autoévaluation client'!D12),0,1) -> 0 | D12: =IF(AND('Autoévaluation client'!D12="",'Autoévaluation client'!E12=""),"*","") -> * | E12: =IF(ISBLANK('Autoévaluation client'!F12),"",'Autoévaluation client'!F12) | M12: 2 | O12: =C12*M12 -> 0 | P12: =L12*M12 -> 0
A13: ='Autoévaluation client'!A13 -> 1.1.8.a | B13: ='Autoévaluation client'!C13 -> L'un des systèmes de management / certifications suivants est-il en vigueur: ISO 9001, ISO 14001, ISO 45001, OHSAS18001 ? Si oui, lequel? | C13: =IF(ISBLANK('Autoévaluation client'!D13),0,1) -> 0 | D13: =IF(AND('Autoévaluation client'!D13="",'Autoévaluation client'!E13=""),"*","") -> * | E13: =IF(ISBLANK('Autoévaluation client'!F13),"",'Autoévaluation client'!F13) | M13: 3 | O13: =C13*M13 -> 0 | P13: =L13*M13 -> 0
A14: ='Autoévaluation client'!A14 -> 1.1.8.b | B14: ='Autoévaluation client'!C14 -> Un autre système de management / certifications est-il en vigueur? Si oui, lequel? | C14: =IF(ISBLANK('Autoévaluation client'!D14),0,1) -> 0 | D14: =IF(AND('Autoévaluation client'!D14="",'Autoévaluation client'!E14=""),"*","") -> * | E14: =IF(ISBLANK('Autoévaluation client'!F14),"",'Autoévaluation client'!F14) | M14: 0 | O14: =C14*M14 -> 0 | P14: =L14*M14 -> 0
A15: ='Autoévaluation client'!A15 -> 1.2. | B15: ='Autoévaluation client'!B15 -> Engagement de la direction | C15: =O15/N15 -> 0 | L15: =P15/N15 -> 0 | M15: 5 | N15: =SUM(M16:M28) -> 14 | O15: =SUM(O16:O28) -> 0 | P15: =SUM(P16:P28) -> 0 | Q15: =O15/$N15*$M15 -> 0 | R15: =P15/$N15*$M15 -> 0
A16: ='Autoévaluation client'!A16 -> 1.2.1. | B16: ='Autoévaluation client'!C16 -> La direction de l'entreprise montre-t-elle l'exemple à suivre en matière de sécurité et de santé à l'aide d'exigences, de décisions, de règles et d'instructions concrètes? | C16: =IF(ISBLANK('Autoévaluation client'!D16),0,1) -> 0 | D16: =IF(AND('Autoévaluation client'!D16="",'Autoévaluation client'!E16=""),"*","") -> * | E16: =IF(ISBLANK('Autoévaluation client'!F16),"",'Autoévaluation client'!F16) | M16: 5 | O16: =M16*C16 -> 0 | P16: =L16*M16 -> 0
A17: ='Autoévaluation client'!A17 -> 1.2.2. | B17: ='Autoévaluation client'!C17 -> Votre entreprise accorde-t-elle à la sécurité au travail la même valeur qu'à la qualité et à la productivité? | C17: =IF(ISBLANK('Autoévaluation client'!D17),0,1) -> 0 | D17: =IF(AND('Autoévaluation client'!D17="",'Autoévaluation client'!E17=""),"*","") -> * | E17: =IF(ISBLANK('Autoévaluation client'!F17),"",'Autoévaluation client'!F17) | M17: 5 | O17: =M17*C17 -> 0 | P17: =L17*M17 -> 0
A18: ='Autoévaluation client'!A18 -> 1.2.3. | B18: ='Autoévaluation client'!C18 -> La direction aborde-t-elle les situations et les comportements à risque lors de ses inspections dans les entreprises? | C18: =IF(ISBLANK('Autoévaluation client'!D18),0,1) -> 0 | D18: =IF(AND('Autoévaluation client'!D18="",'Autoévaluation client'!E18=""),"*","") -> * | E18: =IF(ISBLANK('Autoévaluation client'!F18),"",'Autoévaluation client'!F18) | M18: 3 | O18: =M18*C18 -> 0 | P18: =L18*M18 -> 0
A19: ='Autoévaluation client'!A19 -> 1.2.4. | B19: ='Autoévaluation client'!C19 -> Le budget prévoit-il des ressources pour la sécurité au travail et la protection de la santé? | C19: =IF(ISBLANK('Autoévaluation client'!D19),0,1) -> 0 | D19: =IF(AND('Autoévaluation client'!D19="",'Autoévaluation client'!E19=""),"*","") -> * | E19: =IF(ISBLANK('Autoévaluation client'!F19),"",'Autoévaluation client'!F19) | M19: 1 | O19: =M19*C19 -> 0 | P19: =L19*M19 -> 0
A20: ='Autoévaluation client'!A20 -> 1.2.5.a | B20: ='Autoévaluation client'!C20 -> La direction soutient-elle dans l'entreprise... les évaluations du risque? | C20: =IF(ISBLANK('Autoévaluation client'!D20),0,1) -> 0 | D20: =IF(AND('Autoévaluation client'!D20="",'Autoévaluation client'!E20=""),"*","") -> * | E20: =IF(ISBLANK('Autoévaluation client'!F20),"",'Autoévaluation client'!F20) | M20: 0 | O20: =M20*C20 -> 0 | P20: =L20*M20 -> 0
A21: ='Autoévaluation client'!A21 -> 1.2.5.b | B21: ='Autoévaluation client'!C21 -> les audits, les contrôles? | C21: =IF(ISBLANK('Autoévaluation client'!D21),0,1) -> 0 | D21: =IF(AND('Autoévaluation client'!D21="",'Autoévaluation client'!E21=""),"*","") -> * | E21: =IF(ISBLANK('Autoévaluation client'!F21),"",'Autoévaluation client'!F21) | M21: 0 | O21: =M21*C21 -> 0 | P21: =L21*M21 -> 0
A22: ='Autoévaluation client'!A22 -> 1.2.5.c | B22: ='Autoévaluation client'!C22 -> les analyses d'accidents? | C22: =IF(ISBLANK('Autoévaluation client'!D22),0,1) -> 0 | D22: =IF(AND('Autoévaluation client'!D22="",'Autoévaluation client'!E22=""),"*","") -> * | E22: =IF(ISBLANK('Autoévaluation client'!F22),"",'Autoévaluation client'!F22) | M22: 0 | O22: =M22*C22 -> 0 | P22: =L22*M22 -> 0
A23: ='Autoévaluation client'!A23 -> 1.2.5.d | B23: ='Autoévaluation client'!C23 -> la formation des collaborateurs sur le lieu de travail? | C23: =IF(ISBLANK('Autoévaluation client'!D23),0,1) -> 0 | D23: =IF(AND('Autoévaluation client'!D23="",'Autoévaluation client'!E23=""),"*","") -> * | E23: =IF(ISBLANK('Autoévaluation client'!F23),"",'Autoévaluation client'!F23) | M23: 0 | O23: =M23*C23 -> 0 | P23: =L23*M23 -> 0
A24: ='Autoévaluation client'!A24 -> 1.2.5.e | B24: ='Autoévaluation client'!C24 -> la mise en œuvre de mesures adéquates? | C24: =IF(ISBLANK('Autoévaluation client'!D24),0,1) -> 0 | D24: =IF(AND('Autoévaluation client'!D24="",'Autoévaluation client'!E24=""),"*","") -> * | E24: =IF(ISBLANK('Autoévaluation client'!F24),"",'Autoévaluation client'!F24) | M24: 0 | O24: =M24*C24 -> 0 | P24: =L24*M24 -> 0
A25: ='Autoévaluation client'!A25 -> 1.2.5.f | B25: ='Autoévaluation client'!C25 -> les campagnes en faveur de la sécurité au travail? | C25: =IF(ISBLANK('Autoévaluation client'!D25),0,1) -> 0 | D25: =IF(AND('Autoévaluation client'!D25="",'Autoévaluation client'!E25=""),"*","") -> * | E25: =IF(ISBLANK('Autoévaluation client'!F25),"",'Autoévaluation client'!F25) | M25: 0 | O25: =M25*C25 -> 0 | P25: =L25*M25 -> 0
A26: ='Autoévaluation client'!A26 -> 1.2.5.g | B26: ='Autoévaluation client'!C26 -> les campagnes en faveur de la sécurité durant les loisirs? | C26: =IF(ISBLANK('Autoévaluation client'!D26),0,1) -> 0 | D26: =IF(AND('Autoévaluation client'!D26="",'Autoévaluation client'!E26=""),"*","") -> * | E26: =IF(ISBLANK('Autoévaluation client'!F26),"",'Autoévaluation client'!F26) | M26: 0 | O26: =M26*C26 -> 0 | P26: =L26*M26 -> 0
A27: ='Autoévaluation client'!A27 -> 1.2.5.h | B27: ='Autoévaluation client'!C27 -> la gestion des absences? | C27: =IF(ISBLANK('Autoévaluation client'!D27),0,1) -> 0 | D27: =IF(AND('Autoévaluation client'!D27="",'Autoévaluation client'!E27=""),"*","") -> * | E27: =IF(ISBLANK('Autoévaluation client'!F27),"",'Autoévaluation client'!F27) | M27: 0 | O27: =M27*C27 -> 0 | P27: =L27*M27 -> 0
A28: ='Autoévaluation client'!A28 -> 1.2.5.i | B28: ='Autoévaluation client'!C28 -> autres? Si oui, lesquels? | C28: =IF(ISBLANK('Autoévaluation client'!D28),0,1) -> 0 | D28: =IF(AND('Autoévaluation client'!D28="",'Autoévaluation client'!E28=""),"*","") -> * | E28: =IF(ISBLANK('Autoévaluation client'!F28),"",'Autoévaluation client'!F28) | M28: 0 | O28: =M28*C28 -> 0 | P28: =L28*M28 -> 0
A29: ='Autoévaluation client'!A29 -> 1.3. | B29: ='Autoévaluation client'!B29 -> Engagement des supérieurs hiérarchiques | C29: =O29/N29 -> 0 | L29: =P29/N29 -> 0 | M29: 5 | N29: =SUM(M30:M41) -> 21 | O29: =SUM(O30:O41) -> 0 | P29: =SUM(P30:P41) -> 0 | Q29: =O29/$N29*$M29 -> 0 | R29: =P29/$N29*$M29 -> 0
A30: ='Autoévaluation client'!A30 -> 1.3.1.a | B30: ='Autoévaluation client'!C30 -> Les supérieurs hiérarchiques promeuvent-ils la sécurité et la santé : en se conformant aux prescriptions de sécurité (par ex. le port de l'équipement de protection individuelle (EPI))? | C30: =IF(ISBLANK('Autoévaluation client'!D30),0,1) -> 0 | D30: =IF(AND('Autoévaluation client'!D30="",'Autoévaluation client'!E30=""),"*","") -> * | E30: =IF(ISBLANK('Autoévaluation client'!F30),"",'Autoévaluation client'!F30) | M30: 5 | O30: =M30*C30 -> 0 | P30: =L30*M30 -> 0
A31: ='Autoévaluation client'!A31 -> 1.3.1.b | B31: ='Autoévaluation client'!C31 -> en faisant respecter l'observation des prescriptions de sécurité? | C31: =IF(ISBLANK('Autoévaluation client'!D31),0,1) -> 0 | D31: =IF(AND('Autoévaluation client'!D31="",'Autoévaluation client'!E31=""),"*","") -> * | E31: =IF(ISBLANK('Autoévaluation client'!F31),"",'Autoévaluation client'!F31) | M31: 5 | O31: =M31*C31 -> 0 | P31: =L31*M31 -> 0
A32: ='Autoévaluation client'!A32 -> 1.3.1.c | B32: ='Autoévaluation client'!C32 -> par d'autres formes d'incitations? Si oui, lesquelles? | C32: =IF(ISBLANK('Autoévaluation client'!D32),0,1) -> 0 | D32: =IF(AND('Autoévaluation client'!D32="",'Autoévaluation client'!E32=""),"*","") -> * | E32: =IF(ISBLANK('Autoévaluation client'!F32),"",'Autoévaluation client'!F32) | M32: 0 | O32: =M32*C32 -> 0 | P32: =L32*M32 -> 0
A33: ='Autoévaluation client'!A33 -> 1.3.2.a | B33: ='Autoévaluation client'!C33 -> Les supérieurs hiérarchiques de l'entreprise s'engagent-ils pour la sécurité et la santé des employés, en réalisant... des évaluations de risque? | C33: =IF(ISBLANK('Autoévaluation client'!D33),0,1) -> 0 | D33: =IF(AND('Autoévaluation client'!D33="",'Autoévaluation client'!E33=""),"*","") -> * | E33: =IF(ISBLANK('Autoévaluation client'!F33),"",'Autoévaluation client'!F33) | M33: 0 | O33: =M33*C33 -> 0 | P33: =L33*M33 -> 0
A34: ='Autoévaluation client'!A34 -> 1.3.2.b | B34: ='Autoévaluation client'!C34 -> des audits, des contrôles? | C34: =IF(ISBLANK('Autoévaluation client'!D34),0,1) -> 0 | D34: =IF(AND('Autoévaluation client'!D34="",'Autoévaluation client'!E34=""),"*","") -> * | E34: =IF(ISBLANK('Autoévaluation client'!F34),"",'Autoévaluation client'!F34) | M34: 2 | O34: =M34*C34 -> 0 | P34: =L34*M34 -> 0
A35: ='Autoévaluation client'!A35 -> 1.3.2.c | B35: ='Autoévaluation client'!C35 -> des analyses d'accidents? | C35: =IF(ISBLANK('Autoévaluation client'!D35),0,1) -> 0 | D35: =IF(AND('Autoévaluation client'!D35="",'Autoévaluation client'!E35=""),"*","") -> * | E35: =IF(ISBLANK('Autoévaluation client'!F35),"",'Autoévaluation client'!F35) | M35: 2 | O35: =M35*C35 -> 0 | P35: =L35*M35 -> 0
A36: ='Autoévaluation client'!A36 -> 1.3.2.d | B36: ='Autoévaluation client'!C36 -> de la formation des collaborateurs à la place de travail? | C36: =IF(ISBLANK('Autoévaluation client'!D36),0,1) -> 0 | D36: =IF(AND('Autoévaluation client'!D36="",'Autoévaluation client'!E36=""),"*","") -> * | E36: =IF(ISBLANK('Autoévaluation client'!F36),"",'Autoévaluation client'!F36) | M36: 2 | O36: =M36*C36 -> 0 | P36: =L36*M36 -> 0
A37: ='Autoévaluation client'!A37 -> 1.3.2.e | B37: ='Autoévaluation client'!C37 -> des campagnes en faveur de la sécurité au travail? | C37: =IF(ISBLANK('Autoévaluation client'!D37),0,1) -> 0 | D37: =IF(AND('Autoévaluation client'!D37="",'Autoévaluation client'!E37=""),"*","") -> * | E37: =IF(ISBLANK('Autoévaluation client'!F37),"",'Autoévaluation client'!F37) | M37: 0 | O37: =M37*C37 -> 0 | P37: =L37*M37 -> 0
A38: ='Autoévaluation client'!A38 -> 1.3.2.f | B38: ='Autoévaluation client'!C38 -> des campagnes en faveur de la sécurité durant les loisirs? | C38: =IF(ISBLANK('Autoévaluation client'!D38),0,1) -> 0 | D38: =IF(AND('Autoévaluation client'!D38="",'Autoévaluation client'!E38=""),"*","") -> * | E38: =IF(ISBLANK('Autoévaluation client'!F38),"",'Autoévaluation client'!F38) | M38: 0 | O38: =M38*C38 -> 0 | P38: =L38*M38 -> 0
A39: ='Autoévaluation client'!A39 -> 1.3.2.g | B39: ='Autoévaluation client'!C39 -> la gestion des absences? | C39: =IF(ISBLANK('Autoévaluation client'!D39),0,1) -> 0 | D39: =IF(AND('Autoévaluation client'!D39="",'Autoévaluation client'!E39=""),"*","") -> * | E39: =IF(ISBLANK('Autoévaluation client'!F39),"",'Autoévaluation client'!F39) | M39: 2 | O39: =M39*C39 -> 0 | P39: =L39*M39 -> 0
A40: ='Autoévaluation client'!A40 -> 1.3.2.h | B40: ='Autoévaluation client'!C40 -> d'autres actions? Si oui, lesquelles? | C40: =IF(ISBLANK('Autoévaluation client'!D40),0,1) -> 0 | D40: =IF(AND('Autoévaluation client'!D40="",'Autoévaluation client'!E40=""),"*","") -> * | E40: =IF(ISBLANK('Autoévaluation client'!F40),"",'Autoévaluation client'!F40) | M40: 0 | O40: =M40*C40 -> 0 | P40: =L40*M40 -> 0
A41: ='Autoévaluation client'!A41 -> 1.3.3 | B41: ='Autoévaluation client'!C41 -> Les supérieurs hiérarchiques connaissent-ils les droits et les obligations résultant des exigences légales en matière de sécurité et de santé? | C41: =IF(ISBLANK('Autoévaluation client'!D41),0,1) -> 0 | D41: =IF(AND('Autoévaluation client'!D41="",'Autoévaluation client'!E41=""),"*","") -> * | E41: =IF(ISBLANK('Autoévaluation client'!F41),"",'Autoévaluation client'!F41) | M41: 3 | O41: =M41*C41 -> 0 | P41: =L41*M41 -> 0
A42: ='Autoévaluation client'!A42 -> 1.4. | B42: ='Autoévaluation client'!B42 -> Objectifs de sécurité | C42: =O42/N42 -> 0 | L42: =P42/N42 -> 0 | M42: 2 | N42: =SUM(M43:M55) -> 21 | O42: =SUM(O43:O55) -> 0 | P42: =SUM(P43:P55) -> 0 | Q42: =O42/$N42*$M42 -> 0 | R42: =P42/$N42*$M42 -> 0
A43: ='Autoévaluation client'!A43 -> 1.4.1.a | B43: ='Autoévaluation client'!C43 -> Existe-t-il des objectifs mesurables concernant la limitation de la fréquence* des événements suivants: * Fréquence = nombre d'événements par rapport au temps de travail productif ou nombre d'événements par rapport au nombre de salariés à plein temps durant une période donnée. Accidents professionnels / maladies professionnels? | C43: =IF(ISBLANK('Autoévaluation client'!D43),0,1) -> 0 | D43: =IF(AND('Autoévaluation client'!D43="",'Autoévaluation client'!E43=""),"*","") -> * | E43: =IF(ISBLANK('Autoévaluation client'!F43),"",'Autoévaluation client'!F43) | M43: 5 | O43: =M43*C43 -> 0 | P43: =L43*M43 -> 0
A44: ='Autoévaluation client'!A44 -> 1.4.1.b | B44: ='Autoévaluation client'!C44 -> Accidents non professionnels? | C44: =IF(ISBLANK('Autoévaluation client'!D44),0,1) -> 0 | D44: =IF(AND('Autoévaluation client'!D44="",'Autoévaluation client'!E44=""),"*","") -> * | E44: =IF(ISBLANK('Autoévaluation client'!F44),"",'Autoévaluation client'!F44) | M44: 3 | O44: =M44*C44 -> 0 | P44: =L44*M44 -> 0
A45: ='Autoévaluation client'!A45 -> 1.4.1.c | B45: ='Autoévaluation client'!C45 -> Maladies? | C45: =IF(ISBLANK('Autoévaluation client'!D45),0,1) -> 0 | D45: =IF(AND('Autoévaluation client'!D45="",'Autoévaluation client'!E45=""),"*","") -> * | E45: =IF(ISBLANK('Autoévaluation client'!F45),"",'Autoévaluation client'!F45) | M45: 2 | O45: =M45*C45 -> 0 | P45: =L45*M45 -> 0
A46: ='Autoévaluation client'!A46 -> 1.4.1.d | B46: ='Autoévaluation client'!C46 -> Dommages matériels? | C46: =IF(ISBLANK('Autoévaluation client'!D46),0,1) -> 0 | D46: =IF(AND('Autoévaluation client'!D46="",'Autoévaluation client'!E46=""),"*","") -> * | E46: =IF(ISBLANK('Autoévaluation client'!F46),"",'Autoévaluation client'!F46) | M46: 3 | O46: =M46*C46 -> 0 | P46: =L46*M46 -> 0
A47: ='Autoévaluation client'!A47 -> 1.4.1.e | B47: ='Autoévaluation client'!C47 -> Perturbations? | C47: =IF(ISBLANK('Autoévaluation client'!D47),0,1) -> 0 | D47: =IF(AND('Autoévaluation client'!D47="",'Autoévaluation client'!E47=""),"*","") -> * | E47: =IF(ISBLANK('Autoévaluation client'!F47),"",'Autoévaluation client'!F47) | M47: 0 | O47: =M47*C47 -> 0 | P47: =L47*M47 -> 0
A48: ='Autoévaluation client'!A48 -> 1.4.1.f | B48: ='Autoévaluation client'!C48 -> Autres événements? Si oui, lesquels? | C48: =IF(ISBLANK('Autoévaluation client'!D48),0,1) -> 0 | D48: =IF(AND('Autoévaluation client'!D48="",'Autoévaluation client'!E48=""),"*","") -> * | E48: =IF(ISBLANK('Autoévaluation client'!F48),"",'Autoévaluation client'!F48) | M48: 0 | O48: =M48*C48 -> 0 | P48: =L48*M48 -> 0
A49: ='Autoévaluation client'!A49 -> 1.4.2.a | B49: ='Autoévaluation client'!C49 -> Existe-t-il des objectifs mesurables visant à restreindre la durée des absences consécutives à... des accidents professionnels / maladies professionnels? | C49: =IF(ISBLANK('Autoévaluation client'!D49),0,1) -> 0 | D49: =IF(AND('Autoévaluation client'!D49="",'Autoévaluation client'!E49=""),"*","") -> * | E49: =IF(ISBLANK('Autoévaluation client'!F49),"",'Autoévaluation client'!F49) | M49: 1 | O49: =M49*C49 -> 0 | P49: =L49*M49 -> 0
A50: ='Autoévaluation client'!A50 -> 1.4.2.b | B50: ='Autoévaluation client'!C50 -> des accidents non professionnels? | C50: =IF(ISBLANK('Autoévaluation client'!D50),0,1) -> 0 | D50: =IF(AND('Autoévaluation client'!D50="",'Autoévaluation client'!E50=""),"*","") -> * | E50: =IF(ISBLANK('Autoévaluation client'!F50),"",'Autoévaluation client'!F50) | M50: 1 | O50: =M50*C50 -> 0 | P50: =L50*M50 -> 0
A51: ='Autoévaluation client'!A51 -> 1.4.2.c | B51: ='Autoévaluation client'!C51 -> des maladies? | C51: =IF(ISBLANK('Autoévaluation client'!D51),0,1) -> 0 | D51: =IF(AND('Autoévaluation client'!D51="",'Autoévaluation client'!E51=""),"*","") -> * | E51: =IF(ISBLANK('Autoévaluation client'!F51),"",'Autoévaluation client'!F51) | M51: 3 | O51: =M51*C51 -> 0 | P51: =L51*M51 -> 0
A52: ='Autoévaluation client'!A52 -> 1.4.2.d | B52: ='Autoévaluation client'!C52 -> d'autres événements? Si oui, lesquels? | C52: =IF(ISBLANK('Autoévaluation client'!D52),0,1) -> 0 | D52: =IF(AND('Autoévaluation client'!D52="",'Autoévaluation client'!E52=""),"*","") -> * | E52: =IF(ISBLANK('Autoévaluation client'!F52),"",'Autoévaluation client'!F52) | M52: 0 | O52: =M52*C52 -> 0 | P52: =L52*M52 -> 0
A53: ='Autoévaluation client'!A53 -> 1.4.3. | B53: ='Autoévaluation client'!C53 -> Vos objectifs en matière de sécurité et de santé s'appliquent-ils à l'entreprise dans son ensemble? | C53: =IF(ISBLANK('Autoévaluation client'!D53),0,1) -> 0 | D53: =IF(AND('Autoévaluation client'!D53="",'Autoévaluation client'!E53=""),"*","") -> * | E53: =IF(ISBLANK('Autoévaluation client'!F53),"",'Autoévaluation client'!F53) | M53: 1 | O53: =M53*C53 -> 0 | P53: =L53*M53 -> 0
A54: ='Autoévaluation client'!A54 -> 1.4.4. | B54: ='Autoévaluation client'!C54 -> Vos objectifs en matière de sécurité et de santé s'appliquent-ils à des unités d'organisation spécifiques? | C54: =IF(ISBLANK('Autoévaluation client'!D54),0,1) -> 0 | D54: =IF(AND('Autoévaluation client'!D54="",'Autoévaluation client'!E54=""),"*","") -> * | E54: =IF(ISBLANK('Autoévaluation client'!F54),"",'Autoévaluation client'!F54) | M54: 1 | O54: =M54*C54 -> 0 | P54: =L54*M54 -> 0
A55: ='Autoévaluation client'!A55 -> 1.4.5. | B55: ='Autoévaluation client'!C55 -> Avez-vous la possibilité de comparer les résultats avec des entreprises similaires (même branche)? Si oui, lesquelles? | C55: =IF(ISBLANK('Autoévaluation client'!D55),0,1) -> 0 | D55: =IF(AND('Autoévaluation client'!D55="",'Autoévaluation client'!E55=""),"*","") -> * | E55: =IF(ISBLANK('Autoévaluation client'!F55),"",'Autoévaluation client'!F55) | M55: 1 | O55: =M55*C55 -> 0 | P55: =L55*M55 -> 0
A56: ='Autoévaluation client'!A56 -> 1.5. | B56: ='Autoévaluation client'!B56 -> Elaboration et contrôle des objectifs, stratégie | C56: =O56/N56 -> 0 | L56: =P56/N56 -> 0 | M56: 2 | N56: =SUM(M57:M63) -> 17 | O56: =SUM(O57:O63) -> 0 | P56: =SUM(P57:P63) -> 0 | Q56: =O56/$N56*$M56 -> 0 | R56: =P56/$N56*$M56 -> 0
A57: ='Autoévaluation client'!A57 -> 1.5.1. | B57: ='Autoévaluation client'!C57 -> Un processus est-il défini pour l'élaboration des objectifs de sécurité? | C57: =IF(ISBLANK('Autoévaluation client'!D57),0,1) -> 0 | D57: =IF(AND('Autoévaluation client'!D57="",'Autoévaluation client'!E57=""),"*","") -> * | E57: =IF(ISBLANK('Autoévaluation client'!F57),"",'Autoévaluation client'!F57) | M57: 3 | O57: =M57*C57 -> 0 | P57: =L57*M57 -> 0
A58: ='Autoévaluation client'!A58 -> 1.5.2. | B58: ='Autoévaluation client'!C58 -> Un engagement pour l'amélioration continue du système de sécurité est-elle contenue dans les objectifs? | C58: =IF(ISBLANK('Autoévaluation client'!D58),0,1) -> 0 | D58: =IF(AND('Autoévaluation client'!D58="",'Autoévaluation client'!E58=""),"*","") -> * | E58: =IF(ISBLANK('Autoévaluation client'!F58),"",'Autoévaluation client'!F58) | M58: 3 | O58: =M58*C58 -> 0 | P58: =L58*M58 -> 0
A59: ='Autoévaluation client'!A59 -> 1.5.3. | B59: ='Autoévaluation client'!C59 -> Les cadres, ou leur représentants, participent-ils à l'élaboration des objectifs de sécurité? | C59: =IF(ISBLANK('Autoévaluation client'!D59),0,1) -> 0 | D59: =IF(AND('Autoévaluation client'!D59="",'Autoévaluation client'!E59=""),"*","") -> * | E59: =IF(ISBLANK('Autoévaluation client'!F59),"",'Autoévaluation client'!F59) | M59: 4 | O59: =M59*C59 -> 0 | P59: =L59*M59 -> 0
A60: ='Autoévaluation client'!A60 -> 1.5.4. | B60: ='Autoévaluation client'!C60 -> Les écarts par rapport aux objectifs sont-ils constatés à temps par le biais d'un relevé des événements (ou d'une évaluation intermédiaire des objectifs en cours d'année) s'appliquant à l'entreprise dans son ensemble? | C60: =IF(ISBLANK('Autoévaluation client'!D60),0,1) -> 0 | D60: =IF(AND('Autoévaluation client'!D60="",'Autoévaluation client'!E60=""),"*","") -> * | E60: =IF(ISBLANK('Autoévaluation client'!F60),"",'Autoévaluation client'!F60) | M60: 1 | O60: =M60*C60 -> 0 | P60: =L60*M60 -> 0
A61: ='Autoévaluation client'!A61 -> 1.5.5. | B61: ='Autoévaluation client'!C61 -> Les écarts par rapport aux objectifs sont-ils constatés à temps par le biais d'un relevé des événements (ou d'une évaluation intermédiaire des objectifs en cours d'année) s'appliquant à des unités d'organisation spécifiques (secteur, division)? | C61: =IF(ISBLANK('Autoévaluation client'!D61),0,1) -> 0 | D61: =IF(AND('Autoévaluation client'!D61="",'Autoévaluation client'!E61=""),"*","") -> * | E61: =IF(ISBLANK('Autoévaluation client'!F61),"",'Autoévaluation client'!F61) | M61: 1 | O61: =M61*C61 -> 0 | P61: =L61*M61 -> 0
A62: ='Autoévaluation client'!A62 -> 1.5.6. | B62: ='Autoévaluation client'!C62 -> Lorsque les objectifs ne sont pas atteints, en tirez-vous les conséquences et prenez-vous les mesures correctrices nécessaires? Si oui, lesquelles? | C62: =IF(ISBLANK('Autoévaluation client'!D62),0,1) -> 0 | D62: =IF(AND('Autoévaluation client'!D62="",'Autoévaluation client'!E62=""),"*","") -> * | E62: =IF(ISBLANK('Autoévaluation client'!F62),"",'Autoévaluation client'!F62) | M62: 3 | O62: =M62*C62 -> 0 | P62: =L62*M62 -> 0
A63: ='Autoévaluation client'!A63 -> 1.5.7. | B63: ='Autoévaluation client'!C63 -> Disposez-vous d'une stratégie de sécurité qui vous aide à atteindre vos objectifs de sécurité (p. ex. paquets de mesures prévus à moyen terme, futures tendances, exigences et attentes des parties intéressées) ? Si oui, laquelle? | C63: =IF(ISBLANK('Autoévaluation client'!D63),0,1) -> 0 | D63: =IF(AND('Autoévaluation client'!D63="",'Autoévaluation client'!E63=""),"*","") -> * | E63: =IF(ISBLANK('Autoévaluation client'!F63),"",'Autoévaluation client'!F63) | M63: 2 | O63: =M63*C63 -> 0 | P63: =L63*M63 -> 0
A64: ='Autoévaluation client'!A65 -> 2. | B64: ='Autoévaluation client'!B65 -> Organisation | C64: =O64/N64 -> 0 | L64: =P64/N64 -> 0 | N64: =SUM(M65,M106,M127) -> 7 | O64: =SUM(Q65,Q106,Q127) -> 0 | P64: =SUM(R65,R106,R127) -> 0
A65: ='Autoévaluation client'!A67 -> 2.1. | B65: ='Autoévaluation client'!B67 -> Organisation de l'entreprise | C65: =O65/N65 -> 0 | D65: =IF(ISBLANK('Autoévaluation client'!E67),"",'Autoévaluation client'!E67) | L65: =P65/N65 -> 0 | M65: 3 | N65: =SUM(M66,M73,M91,M103) -> 7 | O65: =SUM(Q66,Q73,Q91,Q103) -> 0 | P65: =SUM(R66,R73,R91,R103) -> 0 | Q65: =O65/$N65*$M65 -> 0 | R65: =P65/$N65*$M65 -> 0
A66: ='Autoévaluation client'!A68 -> 2.1.1 | B66: ='Autoévaluation client'!C68 -> Type d'organisation | C66: =O66/N66 -> 0 | D66: =IF(ISBLANK('Autoévaluation client'!E68),"",'Autoévaluation client'!E68) | L66: =P66/N66 -> 0 | M66: 1 | N66: =MAX(M67:M72) -> 1 | O66: =MAX(O67:O72) -> 0 | P66: =MAX(P67:P72) -> 0 | Q66: =O66/N66*M66 -> 0 | R66: =P66/N66*$M66 -> 0
A67: ='Autoévaluation client'!A69 -> 2.1.1.1.a | B67: ='Autoévaluation client'!C69 -> Quel type d’organisation structurelle existe dans votre entreprise: Organisation hiérarchique? | C67: =IF(ISBLANK('Autoévaluation client'!D69),0,1) -> 0 | D67: =IF(AND('Autoévaluation client'!D69="",'Autoévaluation client'!E69=""),"*","") -> * | E67: =IF(ISBLANK('Autoévaluation client'!F69),"",'Autoévaluation client'!F69) | M67: 1 | O67: =C67*M67 -> 0 | P67: =L67*M67 -> 0
A68: ='Autoévaluation client'!A70 -> 2.1.1.2.b | B68: ='Autoévaluation client'!C70 -> Organisation d’état-major de ligne? | C68: =IF(ISBLANK('Autoévaluation client'!D70),0,1) -> 0 | D68: =IF(AND('Autoévaluation client'!D70="",'Autoévaluation client'!E70=""),"*","") -> * | E68: =IF(ISBLANK('Autoévaluation client'!F70),"",'Autoévaluation client'!F70) | M68: 1 | O68: =C68*M68 -> 0 | P68: =L68*M68 -> 0
A69: ='Autoévaluation client'!A71 -> 2.1.1.2.c | B69: ='Autoévaluation client'!C71 -> Organisation fonctionnelle? | C69: =IF(ISBLANK('Autoévaluation client'!D71),0,1) -> 0 | D69: =IF(AND('Autoévaluation client'!D71="",'Autoévaluation client'!E71=""),"*","") -> * | E69: =IF(ISBLANK('Autoévaluation client'!F71),"",'Autoévaluation client'!F71) | M69: 1 | O69: =C69*M69 -> 0 | P69: =L69*M69 -> 0
A70: ='Autoévaluation client'!A72 -> 2.1.1.2.d | B70: ='Autoévaluation client'!C72 -> Organisation matricielle? | C70: =IF(ISBLANK('Autoévaluation client'!D72),0,1) -> 0 | D70: =IF(AND('Autoévaluation client'!D72="",'Autoévaluation client'!E72=""),"*","") -> * | E70: =IF(ISBLANK('Autoévaluation client'!F72),"",'Autoévaluation client'!F72) | M70: 1 | O70: =C70*M70 -> 0 | P70: =L70*M70 -> 0
A71: ='Autoévaluation client'!A73 -> 2.1.1.2.e | B71: ='Autoévaluation client'!C73 -> Organisation de projets? | C71: =IF(ISBLANK('Autoévaluation client'!D73),0,1) -> 0 | D71: =IF(AND('Autoévaluation client'!D73="",'Autoévaluation client'!E73=""),"*","") -> * | E71: =IF(ISBLANK('Autoévaluation client'!F73),"",'Autoévaluation client'!F73) | M71: 1 | O71: =C71*M71 -> 0 | P71: =L71*M71 -> 0
A72: ='Autoévaluation client'!A74 -> 2.1.1.2.f | B72: ='Autoévaluation client'!C74 -> Autre forme? Si oui, laquelle? | C72: =IF(ISBLANK('Autoévaluation client'!D74),0,1) -> 0 | D72: =IF(AND('Autoévaluation client'!D74="",'Autoévaluation client'!E74=""),"*","") -> * | E72: =IF(ISBLANK('Autoévaluation client'!F74),"",'Autoévaluation client'!F74) | M72: 1 | O72: =C72*M72 -> 0 | P72: =L72*M72 -> 0
A73: ='Autoévaluation client'!A75 -> 2.1.2. | B73: ='Autoévaluation client'!C75 -> Tâches, compétences, responsabilités | C73: =O73/N73 -> 0 | D73: =IF(ISBLANK('Autoévaluation client'!E75),"",'Autoévaluation client'!E75) | E73: =IF(ISBLANK('Autoévaluation client'!F75),"",'Autoévaluation client'!F75) | L73: =P73/N73 -> 0 | M73: 3 | N73: =SUM(M74:M90) -> 21 | O73: =SUM(O74:O90) -> 0 | P73: =SUM(P74:P90) -> 0 | Q73: =O73/$N73*$M73 -> 0 | R73: =P73/$N73*$M73 -> 0
A74: ='Autoévaluation client'!A76 -> 2.1.2.1. | B74: ='Autoévaluation client'!C76 -> Les compétences et les responsabilités concernant la sécurité et la santé des collaborateurs sont-elles définies par écrit? | C74: =IF(ISBLANK('Autoévaluation client'!D76),0,1) -> 0 | D74: =IF(AND('Autoévaluation client'!D76="",'Autoévaluation client'!E76=""),"*","") -> * | E74: =IF(ISBLANK('Autoévaluation client'!F76),"",'Autoévaluation client'!F76) | M74: 4 | O74: =C74*M74 -> 0 | P74: =L74*M74 -> 0
A75: ='Autoévaluation client'!A77 -> 2.1.2.2.a | B75: ='Autoévaluation client'!C77 -> Votre entreprise dispose-t-elle de documents d'organisation tels que: Descriptions des postes de travail? | C75: =IF(ISBLANK('Autoévaluation client'!D77),0,1) -> 0 | D75: =IF(AND('Autoévaluation client'!D77="",'Autoévaluation client'!E77=""),"*","") -> * | E75: =IF(ISBLANK('Autoévaluation client'!F77),"",'Autoévaluation client'!F77) | M75: 2 | O75: =C75*M75 -> 0 | P75: =L75*M75 -> 0
A76: ='Autoévaluation client'!A78 -> 2.1.2.2.b | B76: ='Autoévaluation client'!C78 -> Cahiers des charges? | C76: =IF(ISBLANK('Autoévaluation client'!D78),0,1) -> 0 | D76: =IF(AND('Autoévaluation client'!D78="",'Autoévaluation client'!E78=""),"*","") -> * | E76: =IF(ISBLANK('Autoévaluation client'!F78),"",'Autoévaluation client'!F78) | M76: 1 | O76: =C76*M76 -> 0 | P76: =L76*M76 -> 0
A77: ='Autoévaluation client'!A79 -> 2.1.2.2.c | B77: ='Autoévaluation client'!C79 -> Diagrammes fonctionnels | C77: =IF(ISBLANK('Autoévaluation client'!D79),0,1) -> 0 | D77: =IF(AND('Autoévaluation client'!D79="",'Autoévaluation client'!E79=""),"*","") -> * | E77: =IF(ISBLANK('Autoévaluation client'!F79),"",'Autoévaluation client'!F79) | M77: 0 | O77: =C77*M77 -> 0 | P77: =L77*M77 -> 0
A78: ='Autoévaluation client'!A80 -> 2.1.2.2.d | B78: ='Autoévaluation client'!C80 -> Règlements? | C78: =IF(ISBLANK('Autoévaluation client'!D80),0,1) -> 0 | D78: =IF(AND('Autoévaluation client'!D80="",'Autoévaluation client'!E80=""),"*","") -> * | E78: =IF(ISBLANK('Autoévaluation client'!F80),"",'Autoévaluation client'!F80) | M78: 2 | O78: =C78*M78 -> 0 | P78: =L78*M78 -> 0
A79: ='Autoévaluation client'!A81 -> 2.1.2.2.e | B79: ='Autoévaluation client'!C81 -> Contrats de travail individuels? | C79: =IF(ISBLANK('Autoévaluation client'!D81),0,1) -> 0 | D79: =IF(AND('Autoévaluation client'!D81="",'Autoévaluation client'!E81=""),"*","") -> * | E79: =IF(ISBLANK('Autoévaluation client'!F81),"",'Autoévaluation client'!F81) | M79: 2 | O79: =C79*M79 -> 0 | P79: =L79*M79 -> 0
A80: ='Autoévaluation client'!A82 -> 2.1.2.2.f | B80: ='Autoévaluation client'!C82 -> Contrats de travail collectifs? | C80: =IF(ISBLANK('Autoévaluation client'!D82),0,1) -> 0 | D80: =IF(AND('Autoévaluation client'!D82="",'Autoévaluation client'!E82=""),"*","") -> * | E80: =IF(ISBLANK('Autoévaluation client'!F82),"",'Autoévaluation client'!F82) | M80: 0 | O80: =C80*M80 -> 0 | P80: =L80*M80 -> 0
A81: ='Autoévaluation client'!A83 -> 2.1.2.2.g | B81: ='Autoévaluation client'!C83 -> Contrats d'entreprise? | C81: =IF(ISBLANK('Autoévaluation client'!D83),0,1) -> 0 | D81: =IF(AND('Autoévaluation client'!D83="",'Autoévaluation client'!E83=""),"*","") -> * | E81: =IF(ISBLANK('Autoévaluation client'!F83),"",'Autoévaluation client'!F83) | M81: 1 | O81: =C81*M81 -> 0 | P81: =L81*M81 -> 0
A82: ='Autoévaluation client'!A84 -> 2.1.2.2.h | B82: ='Autoévaluation client'!C84 -> Autres documents d'organisation? Si oui, lesquels? | C82: =IF(ISBLANK('Autoévaluation client'!D84),0,1) -> 0 | D82: =IF(AND('Autoévaluation client'!D84="",'Autoévaluation client'!E84=""),"*","") -> * | E82: =IF(ISBLANK('Autoévaluation client'!F84),"",'Autoévaluation client'!F84) | M82: 0 | O82: =C82*M82 -> 0 | P82: =L82*M82 -> 0
A83: ='Autoévaluation client'!A85 -> 2.1.2.3.a | B83: ='Autoévaluation client'!C85 -> Les tâches, compétences, responsabilités (obligations et droits) concernant la sécurité et la santé font-elles partie des documents suivants: Descriptions des postes? | C83: =IF(ISBLANK('Autoévaluation client'!D85),0,1) -> 0 | D83: =IF(AND('Autoévaluation client'!D85="",'Autoévaluation client'!E85=""),"*","") -> * | E83: =IF(ISBLANK('Autoévaluation client'!F85),"",'Autoévaluation client'!F85) | M83: 5 | O83: =C83*M83 -> 0 | P83: =L83*M83 -> 0
A84: ='Autoévaluation client'!A86 -> 2.1.2.3.b | B84: ='Autoévaluation client'!C86 -> Cahiers des charges? | C84: =IF(ISBLANK('Autoévaluation client'!D86),0,1) -> 0 | D84: =IF(AND('Autoévaluation client'!D86="",'Autoévaluation client'!E86=""),"*","") -> * | E84: =IF(ISBLANK('Autoévaluation client'!F86),"",'Autoévaluation client'!F86) | M84: 1 | O84: =C84*M84 -> 0 | P84: =L84*M84 -> 0
A85: ='Autoévaluation client'!A87 -> 2.1.2.3.c | B85: ='Autoévaluation client'!C87 -> Diagrammes fonctionnels | C85: =IF(ISBLANK('Autoévaluation client'!D87),0,1) -> 0 | D85: =IF(AND('Autoévaluation client'!D87="",'Autoévaluation client'!E87=""),"*","") -> * | E85: =IF(ISBLANK('Autoévaluation client'!F87),"",'Autoévaluation client'!F87) | M85: 0 | O85: =C85*M85 -> 0 | P85: =L85*M85 -> 0
... A90: ='Autoévaluation client'!A92 -> 2.1.2.3.h | B90: ='Autoévaluation client'!C92 -> Autres documents d'organisation? Si oui, lesquels? | C90: =IF(ISBLANK('Autoévaluation client'!D92),0,1) -> 0 | D90: =IF(AND('Autoévaluation client'!D92="",'Autoévaluation client'!E92=""),"*","") -> * | E90: =IF(ISBLANK('Autoévaluation client'!F92),"",'Autoévaluation client'!F92) | M90: 0 | O90: =C90*M90 -> 0 | P90: =L90*M90 -> 0
A91: ='Autoévaluation client'!A93 -> 2.1.3. | B91: ='Autoévaluation client'!C93 -> Planification et organisation du travail | C91: =O91/N91 -> 0 | D91: =IF(ISBLANK('Autoévaluation client'!E93),"",'Autoévaluation client'!E93) | E91: =IF(ISBLANK('Autoévaluation client'!F93),"",'Autoévaluation client'!F93) | L91: =P91/N91 -> 0 | M91: 2 | N91: =SUM(M92:M102) -> 17 | O91: =SUM(O92:O102) -> 0 | P91: =SUM(P92:P102) -> 0 | Q91: =O91/$N91*$M91 -> 0 | R91: =P91/$N91*$M91 -> 0
A92: ='Autoévaluation client'!A94 -> 2.1.3.1.a | B92: ='Autoévaluation client'!C94 -> La planification, le calcul, l'organisation et la préparation des ordres de travail sont-ils effectués par : Les supérieurs hiérarchiques? | C92: =IF(ISBLANK('Autoévaluation client'!D94),0,1) -> 0 | D92: =IF(AND('Autoévaluation client'!D94="",'Autoévaluation client'!E94=""),"*","") -> * | E92: =IF(ISBLANK('Autoévaluation client'!F94),"",'Autoévaluation client'!F94) | M92: 3 | O92: =C92*M92 -> 0 | P92: =L92*M92 -> 0
A93: ='Autoévaluation client'!A95 -> 2.1.3.1.b | B93: ='Autoévaluation client'!C95 -> Des teams de projet? | C93: =IF(ISBLANK('Autoévaluation client'!D95),0,1) -> 0 | D93: =IF(AND('Autoévaluation client'!D95="",'Autoévaluation client'!E95=""),"*","") -> * | E93: =IF(ISBLANK('Autoévaluation client'!F95),"",'Autoévaluation client'!F95) | M93: 0 | O93: =C93*M93 -> 0 | P93: =L93*M93 -> 0
A94: ='Autoévaluation client'!A96 -> 2.1.3.1.c | B94: ='Autoévaluation client'!C96 -> D’une unité organisationnelle spéciale (AVOR / Préparation du travail)? | C94: =IF(ISBLANK('Autoévaluation client'!D96),0,1) -> 0 | D94: =IF(AND('Autoévaluation client'!D96="",'Autoévaluation client'!E96=""),"*","") -> * | E94: =IF(ISBLANK('Autoévaluation client'!F96),"",'Autoévaluation client'!F96) | M94: 0 | O94: =C94*M94 -> 0 | P94: =L94*M94 -> 0
A95: ='Autoévaluation client'!A97 -> 2.1.3.1.d | B95: ='Autoévaluation client'!C97 -> Autres organes/personnes? Si oui, quels organes/personnes? | C95: =IF(ISBLANK('Autoévaluation client'!D97),0,1) -> 0 | D95: =IF(AND('Autoévaluation client'!D97="",'Autoévaluation client'!E97=""),"*","") -> * | E95: =IF(ISBLANK('Autoévaluation client'!F97),"",'Autoévaluation client'!F97) | M95: 0 | O95: =C95*M95 -> 0 | P95: =L95*M95 -> 0
A96: ='Autoévaluation client'!A98 -> 2.1.3.2. | B96: ='Autoévaluation client'!C98 -> Des aspects de la sécurité au travail et de la protection de la santé sont-ils pris en considération au cours des phases de la planification, de l'organisation et de la préparation du travail? | C96: =IF(ISBLANK('Autoévaluation client'!D98),0,1) -> 0 | D96: =IF(AND('Autoévaluation client'!D98="",'Autoévaluation client'!E98=""),"*","") -> * | E96: =IF(ISBLANK('Autoévaluation client'!F98),"",'Autoévaluation client'!F98) | M96: 5 | O96: =C96*M96 -> 0 | P96: =L96*M96 -> 0
A97: ='Autoévaluation client'!A99 -> 2.1.3.3. | B97: ='Autoévaluation client'!C99 -> Existe-t-il une séparation stricte entre la planification, l'organisation, la préparation et l'exécution des travaux? | C97: =IF(ISBLANK('Autoévaluation client'!D99),0,1) -> 0 | D97: =IF(AND('Autoévaluation client'!D99="",'Autoévaluation client'!E99=""),"*","") -> * | E97: =IF(ISBLANK('Autoévaluation client'!F99),"",'Autoévaluation client'!F99) | M97: 0 | O97: =C97*M97 -> 0 | P97: =L97*M97 -> 0
A98: ='Autoévaluation client'!A100 -> 2.1.3.4. | B98: ='Autoévaluation client'!C100 -> Le niveau opérationnel est impliqué dans la préparation au travail? | C98: =IF(ISBLANK('Autoévaluation client'!D100),0,1) -> 0 | D98: =IF(AND('Autoévaluation client'!D100="",'Autoévaluation client'!E100=""),"*","") -> * | E98: =IF(ISBLANK('Autoévaluation client'!F100),"",'Autoévaluation client'!F100) | M98: 0 | O98: =C98*M98 -> 0 | P98: =L98*M98 -> 0
A99: ='Autoévaluation client'!A101 -> 2.1.3.5. | B99: ='Autoévaluation client'!C101 -> Le travail à exécuter est-il expliqué et discuté? | C99: =IF(ISBLANK('Autoévaluation client'!D101),0,1) -> 0 | D99: =IF(AND('Autoévaluation client'!D101="",'Autoévaluation client'!E101=""),"*","") -> * | E99: =IF(ISBLANK('Autoévaluation client'!F101),"",'Autoévaluation client'!F101) | M99: 3 | O99: =C99*M99 -> 0 | P99: =L99*M99 -> 0
A100: ='Autoévaluation client'!A102 -> 2.1.3.6. | B100: ='Autoévaluation client'!C102 -> La sécurité et la protection de la santé sont-elles intégrées dans le travail à exécuter? | C100: =IF(ISBLANK('Autoévaluation client'!D102),0,1) -> 0 | D100: =IF(AND('Autoévaluation client'!D102="",'Autoévaluation client'!E102=""),"*","") -> * | E100: =IF(ISBLANK('Autoévaluation client'!F102),"",'Autoévaluation client'!F102) | M100: 3 | O100: =C100*M100 -> 0 | P100: =L100*M100 -> 0
A101: ='Autoévaluation client'!A103 -> 2.1.3.7. | B101: ='Autoévaluation client'!C103 -> Les ordres de travail sont-ils donnés et documentés sous forme écrite ? | C101: =IF(ISBLANK('Autoévaluation client'!D103),0,1) -> 0 | D101: =IF(AND('Autoévaluation client'!D103="",'Autoévaluation client'!E103=""),"*","") -> * | E101: =IF(ISBLANK('Autoévaluation client'!F103),"",'Autoévaluation client'!F103) | M101: 2 | O101: =C101*M101 -> 0 | P101: =L101*M101 -> 0
A102: ='Autoévaluation client'!A104 -> 2.1.3.8. | B102: ='Autoévaluation client'!C104 -> Les instructions de travail écrites font-elles référence à des mesures de sécurité et de protection de la santé? | C102: =IF(ISBLANK('Autoévaluation client'!D104),0,1) -> 0 | D102: =IF(AND('Autoévaluation client'!D104="",'Autoévaluation client'!E104=""),"*","") -> * | E102: =IF(ISBLANK('Autoévaluation client'!F104),"",'Autoévaluation client'!F104) | M102: 1 | O102: =C102*M102 -> 0 | P102: =L102*M102 -> 0
A103: ='Autoévaluation client'!A105 -> 2.1.4. | B103: ='Autoévaluation client'!C105 -> Règlement d'entreprise | C103: =O103/N103 -> 0 | D103: =IF(ISBLANK('Autoévaluation client'!E105),"",'Autoévaluation client'!E105) | E103: =IF(ISBLANK('Autoévaluation client'!F105),"",'Autoévaluation client'!F105) | L103: =P103/N103 -> 0 | M103: 1 | N103: =MAX(M104:M105) -> 1 | O103: =MAX(O104:O105) -> 0 | P103: =MAX(P104:P105) -> 0 | Q103: =O103/N103*M103 -> 0 | R103: =P103/N103*$M103 -> 0
A104: ='Autoévaluation client'!A106 -> 2.1.4.1. | B104: ='Autoévaluation client'!C106 -> Votre entreprise dispose-t-elle d'un règlement d'entreprise obligatoire conformément à la loi sur le travail? | C104: =IF(ISBLANK('Autoévaluation client'!D106),0,1) -> 0 | D104: =IF(AND('Autoévaluation client'!D106="",'Autoévaluation client'!E106=""),"*","") -> * | E104: =IF(ISBLANK('Autoévaluation client'!F106),"",'Autoévaluation client'!F106) | M104: 1 | O104: =C104*M104 -> 0 | P104: =L104*M104 -> 0
...

Sheet Auswertungen
B2: Legende im Spinnendiagramm:
A3: Erfüllungsgrad | B3: ="Autoévaluation "&Analyse!B1 -> Autoévaluation Exemple SA | D3: Évaluation Suva | G3: Delta Suva - Kunde
B4: Berechnung automatisch | C4: Spinnendiagramm überschreibbar | D4: Berechnung automatisch | E4: Spinnendiagramm überschreibbar | G4: Zur Information
A5: =CONCATENATE(Analyse!A4," ",Analyse!B4) -> 1 Ligne de conduite, objectifs et stratégie | B5: =Analyse!C4 -> 0 | C5: =B5 -> 0 | D5: =Analyse!L4 -> 0 | E5: =D5 -> 0 | G5: =E5-C5 -> 0
A6: =CONCATENATE(Analyse!A64," ",Analyse!B64) -> 2. Organisation | B6: =Analyse!C64 -> 0 | C6: =B6 -> 0 | D6: =Analyse!L64 -> 0 | E6: =D6 -> 0 | G6: =E6-C6 -> 0
A7: =CONCATENATE(Analyse!A144," ",Analyse!B144) -> 3. Qualification, formation, communication | B7: =Analyse!C144 -> 0 | C7: =B7 -> 0 | D7: =Analyse!L144 -> 0 | E7: =D7 -> 0 | G7: =E7-C7 -> 0
A8: =CONCATENATE(Analyse!A240," ",Analyse!B240) -> 4. Règles de sécurité | B8: =Analyse!C240 -> 0.5 | C8: =B8 -> 0.5 | D8: =Analyse!L240 -> 0 | E8: =D8 -> 0 | G8: =E8-C8 -> -0.5
A9: =CONCATENATE(Analyse!A319," ",Analyse!B319) -> 5. Détermination des phénomènes dangereux et évaluation des risques | B9: =Analyse!C319 -> 0.034090909 | C9: =B9 -> 0.034090909 | D9: =Analyse!L319 -> 0.034090909 | E9: =D9 -> 0.034090909 | G9: =E9-C9 -> 0
A10: =CONCATENATE(Analyse!A368," ",Analyse!B368) -> 6. Mesures | B10: =Analyse!C368 -> 0 | C10: =B10 -> 0 | D10: =Analyse!L368 -> 0 | E10: =D10 -> 0 | G10: =E10-C10 -> 0
A11: =CONCATENATE(Analyse!A392," ",Analyse!B392) -> 7. Organisation en cas d’urgence | B11: =Analyse!C392 -> 0 | C11: =B11 -> 0 | D11: =Analyse!L392 -> 0 | E11: =D11 -> 0 | G11: =E11-C11 -> 0
A12: =CONCATENATE(Analyse!A429," ",Analyse!B429) -> 8. Participation | B12: =Analyse!C429 -> 0 | C12: =B12 -> 0 | D12: =Analyse!L429 -> 0 | E12: =D12 -> 0 | G12: =E12-C12 -> 0
A13: =CONCATENATE(Analyse!A445," ",Analyse!B445) -> 9. Protection de la santé | B13: =Analyse!C445 -> 0.15227273 | C13: =B13 -> 0.15227273 | D13: =Analyse!L445 -> 0.15227273 | E13: =D13 -> 0.15227273 | G13: =E13-C13 -> 0
A14: =CONCATENATE(Analyse!A556," ",Analyse!B556) -> 10. Contrôle, audit | B14: =Analyse!C556 -> 0 | C14: =B14 -> 0 | D14: =Analyse!L556 -> 0 | E14: =D14 -> 0 | G14: =E14-C14 -> 0
A15: =CONCATENATE(Analyse!A587," ",Analyse!B587) -> 11. Gestion des absences | B15: =Analyse!C587 -> 0 | C15: =B15 -> 0 | D15: =Analyse!L587 -> 0 | E15: =D15 -> 0 | G15: =E15-C15 -> 0
A16: =CONCATENATE(Analyse!A607," ",Analyse!B607) -> 12 Sécurité durant les loisirs (facultatif) | B16: =Analyse!C607 -> 0 | C16: =B16 -> 0 | D16: =Analyse!L607 -> 0 | E16: =D16 -> 0 | G16: =E16-C16 -> 0
A17: =CONCATENATE(Analyse!A629," ",Analyse!B629) -> 13 GSE: Gestion de la santé en entreprise (facultatif) | B17: =Analyse!C629 -> 0 | C17: =B17 -> 0 | D17: =Analyse!L629 -> 0 | E17: =D17 -> 0 | G17: =E17-C17 -> 0
A18: =CONCATENATE(Analyse!A657," ",Analyse!B657) -> 14 Extension pour ISO 45001 (facultatif) | B18: =Analyse!C657 -> 0 | C18: =B18 -> 0 | D18: =Analyse!L657 -> 0 | E18: =D18 -> 0 | G18: =E18-C18 -> 0

Sheet Versionenprotokoll
A1: Versionenprotokoll
A3: Version | B3: Sheet | C3: Änderungen
A4: Version 14 | B4: Selbstbeurteilung Kunde | C4: Französische Übersetzung der Frage 2.3.2.3. korrigiert
A5: Freigabe
A6: 45061
B7: Anleitung | C7: Versionnummer aktualisiert
B8: Selbstbeurteilung Kunde | C8: Versionnummer aktualisiert
A9: Version 13 | B9: verschiedene | C9: Formulierungen in der französischen Version kontrolliert und korrigiert durch Sandrine Casanova.
A10: Freigabe
A11: 45028
B12: Anleitung | C12: Versionnummer aktualisiert
B13: Selbstbeurteilung Kunde | C13: Versionnummer aktualisiert
A14: Version 12 | B14: Selbstbeurteilung Kunde | C14: In Fusszeile des Ausdrucks Versionnummer aktualisiert
A15: Freigabe | B15: Anleitung | C15: Versionnummer aktualisiert
A16: 44841 | B16: Analyse | C16: Spalte D "*" eingefügt zur Visualisierung nicht beantwortet.
B17: Analyse | C17: Spalte C formatiert für Visualisierung Ja / Nein
B18: Selbstbeurteilung Kunde | C18: In 9.9.8 und 9.9.9 Fragen 9.9 und 9.3 aus dem ASA-Systemkontrolle Kategorie 3.1 (EKAS 6074/3.1.d 02.2021) eingefügt.
A20: Version 11 | B20: Selbstbeurteilung Kunde | C20: In Fusszeile des Ausdrucks Versionnummer aktualisiert
A21: Freigabe | B21: Anleitung | C21: Versionnummer aktualisiert
A22: 43712 | B22: Selbstbeurteilung Kunde | C22: Anpassung von OHSAS 18001 auf ISO 45001
B23: Generell | C23: Suva Logo aktualisiert
B24: Analyse | C24: Anpassungen von OHSAS 18001 auf ISO 45001
A25: Version 10 | B25: Selbstbeurteilung Kunde | C25: In Fusszeile des Ausdrucks Versionnummer aktualisiert
A26: Freigabe | B26: Anleitung | C26: Versionnummer aktualisiert
A27: 42548 | B27: Analyse | C27: 2.1.3. Gewicht von 1 auf 2 erhöht
B28: Analyse | C28: 1.1.7. Gewicht von 5 auf 2 reduziert
B29: Analyse | C29: 4.1.3. Gewicht von 3 auf 1 reduziert
B30: Analyse | C30: 3.1. falscher Titel korrigiert (Zellenbezug 149 anstatt 148)
B31: Analyse | C31: 4.2. Gewicht von 1 auf 0 reduziert
B32: Analyse | C32: 4.3. Gewicht von 1 auf 2 erhöht
B33: Spinnendiagramme | C33: Legende "Beurteilung Suva" von D3 in Sheet Auswertungen
A35: Version 09 | B35: Selbstbeurteilung Kunde | C35: In Fusszeile des Ausdrucks Versionnummer aktualisiert
A36: Freigabe | B36: Anleitung | C36: Versionnummer aktualisiert
A37: 42555 | B37: Analyse | C37: Gewicht von Kapitel 9.3. physische Belastungen von 3 auf 0 geändert
B38: Analyse | C38: 9.10. Summierung der eigenen Punkte: Formel auf richtige Spalte korrigiert
B39: Analyse | C39: 4.8. Bewertung für Stichproben eingeführt
B40: Analyse | C40: 4.1.3 Gewicht für Booklet von 5 auf 3 reduziert
B41: Diagramme | C41: Rahmenlinie entfernt
A42: Version 08 | B42: Selbstbeurteilung Kunde | C42: In Fusszeile des Ausdrucks Versionnummer aktualisiert
A43: Freigabe | B43: Anleitung | C43: Versionnummer aktualisiert
A44: 42499 | B44: Analyse | C44: Berechnung der PunkteN und O in Zeile 144 für Kapitel 3 bis Zelle 239 korrigiert
A46: Version 07 | B46: Selbstbeurteilung Kunde | C46: In Fusszeile des Ausdrucks Versionnummer aktualisiert
A47: Freigabe | B47: Anleitung | C47: Versionnummer aktualisiert
A48: 42492 | B48: Betriebsspiegel | C48: Fehler in der Nummerierung korrigiert
B49: Analyse | C49: Verdeckte Spalten gelöscht
B50: Analyse | C50: Druckbereich festgelegt
B51: Tabelle 1 | C51: wieder entfernt
A53: Version 06 | B53: Selbstbeurteilung Kunde | C53: In Fusszeile des Ausdrucks Versionnummer aktualisiert
A54: Freigabe | B54: Anleitung | C54: Versionnummer aktualisiert
A55: 42458 | B55: Anleitung | C55: "ist" in Punkt 3 gelöscht.
B56: Schlüsselpersonen Sicherheit | C56: Sicherheitsorganisation: "extern" bei ASA-Spezialisten ergänzt
B57: Betriebsspiegel | C57: Zeile "18. Nettoprämiensatz …" gelöscht
A59: Version 05 | B59: Selbstbeurteilung Kunde | C59: In Fusszeile des Ausdrucks Versionnummer aktualisiert
A60: Freigabe | B60: Anleitung | C60: Versionnummer aktualisiert
A61: 42437 | B61: Analyse | C61: Berechnungen der Unterkapitelbewertungen für die verschiedenen Stufen in den Kapiteln 1 und 2 korrigiert
B62: Analyse | C62: Berechnung der Unterkapitelbewertungen an verschiedenen Orten in den Kapitel 3-11 korrigiert
B63: Analyse | C63: Bezug im Kapitel 10.3.2. korrigiert
B64: Analyse | C64: Feldfarbe für ja bei 10.3.1. auch auf grau gesetzt
A66: Version 04 | B66: Anleitung | C66: Punkt 5 " Beantworten …." : Text korrigiert
B67: Spinne ohne FZ, BGM, OHSAS | C67: Kundenname in Legende integriert. Quelle für Legendentitel ist aus Auswertungen C3
A68: Freigabe | B68: Spinne mit FZ, BGM, OHSAS | C68: Kundenname in Legende integriert. Quelle für Legendentitel ist aus Auswertungen C3
A69: 42401 | B69: Auswertungen | C69: Quelle des Kundenamen für Titel in C3 ist Firmenname im Betriebsspiegel.
B70: Versionenprotokoll | C70: neu erstellt
B71: Selbstbeurteilung Kunde | C71: In Fusszeile des Ausdrucks Versionnummer aktualisiert
B72: Anleitung | C72: Versionnummer ergänzt und aktualisiert
A74: Version 03 | C74: Kapitel Freizeitsicherheit ergänzt
A75: Freigabe | C75: Kapitel BGM ergänzt
A76: 42352 | C76: Verschiedene Fehler gemäss vbr korrigiert
