Workbook
Name Spinne1: Analyse!$C$4

Sheet Guida
A1: Istruzioni per il questionario "Autovalutazione"
A2: Introduzione Avete deciso di migliorare sistematicamente la sicurezza sul lavoro e la tutela della salute nella vostra azienda facendo ricorso al progetto "sicurezza integrata". Il presente questionario costituisce un elemento centrale del progetto perché permette di verificare lo stato della sicurezza sul lavoro e tutela della salute nella vostra azienda e di raccogliere le informazioni necessarie per il progetto. Le seguenti note servono ad aiutarvi nella compilazione del questionario.
A3: 1. Struttura del questionario - Fogli di lavoro: - Dati aziendali - Figure chiave per la sicurezza sul lavoro - Autovalutazione cliente - Allegati (informazione)
A4: 2. Struttura dei singoli fogli di lavoro - È possibile compilare solo le celle previste a questo scopo; tutte le altre sono bloccate. - Le celle da compilare sono evidenziate in grigio. - Se necessario, è possibile compilare tutti gli altri campi sbloccati. - Utilizzare il tabulatore per passare da un campo all'altro.
A5: 3. Foglio di lavoro "Dati aziendali" - Inserire le informazioni richieste nella colonna "Annotazioni cliente".
A6: 4. Foglio di lavoro "Figure chiave per la sicurezza" - Indicare le funzioni presenti in azienda nella colonna "Funzione / competenza". - Compilare la colonna "Cognome / nome" per tutte le "funzioni / competenze" presenti in azienda.
A7: 5. Foglio di lavoro "Autovalutazione cliente" - Rispondere con "sì" o "no" a tutte le domande, mettendo una "x" sulla relativa casella - I commenti si possono scrivere nella colonna "Osservazione cliente". - A seconda della risposta, può risultare necessario inserire un commento alla risposta sì/no (colonna "Osservazione cliente" evidenziata in grigio). - Alcune domande si compongono di varie domande parziali. - In questi casi la domanda è evidenziata su sfondo azzurro.
A8: 6. Allegati - Per alcune domande nel foglio di lavoro "Autovalutazione cliente" si richiede obbligatoriamente di allegare la documentazione (se presente). - Il numero del rispettivo allegato va indicato nella colonna "Allegati richiesti". - Nel foglio di lavoro "Allegati" si illustrano i codici degli allegati. - Se necessario, si possono aggiungere altri allegati. - Si prega di inviare gli allegati nel formato PDF.
A9: FO.250.i.V14

Sheet Dati aziendali
A1: Dati aziendali
C2: Annotazione cliente:
A3: 1. Nome | C3: Muster AG
A4: 2. Sede principale
A5: 3. Fondazione
A6: 4. Altre sedi
A7: 5. Forma giuridica
A8: 6. Propietario
A9: 7. Organi
A10: 8. Prodotti
A11: 9. Clienti
A12: 10. Certificati tutela ambiente e qualità
A13: 11. Documenti aziendali
A14: 12. Unità organizzative dell'azienda e numero di dipendenti in ogni unità organizzative
A15: 13. Ampiezza di supervisione* nella vostra azienda *Ampiezza di supervisione: Numero dei diretti subordinati di un superiore | B15: a livello di top management
B16: a livello dirigenziale superiore
B17: a livello dirigenziale inferiore
A18: 14. Numero di dipendenti | B18: Direzione
B19: Quadri
B20: Collaboratori
B21: Apprendisti
B22: dipendenti totale
A23: 15. Tendenza di sviluppo numero di dipendenti (aumento / costante / diminuzione) | B23: Quadri
B24: Collaboratori
B25: Apprendisti
B26: Totale
A27: 16. Livello d’istruzione dei dipendenti (in %) | B27: Diploma universitario
B28: Formazione superiore (scuola politecnica / SUPSI)
B29: Formazione professionale
B30: Formazione breve
A31: 17. Nazionalità del personale
A32: 18. Lingua madre del personale
A33: 19. Pericoli principali in azienda

Sheet Persone chiavi per la sicurezza
A1: Persone chiavi per la sicurezza
A2: Funzione/competenza | B2: Cognome/nome
A3: Direzione
A14: Capo divisione (se non indicato nell'organigramma)
A26: Resp. progetto (capo progetto) / team SI
A37: Organizzazione della sicurezza
A38: Addetto/preposto alla sicurezza
A39: Ingegnere di sicurezza
A40: Esperto nell'ambito della sicurezza
A41: Assistente alla sicurezza
A42: Esperto in ergonomia
A43: Esperto di prodotti chimici
A44: Resp. radioprotezione
A45: Specialista MSSL
... A121: Altre figure chiave (se necessario compilare)

Sheet Autovalutazione
A1: Autovalutazione cliente
A2: N° | C2: Descrizione domanda | D2: Sì | E2: No | F2: Osservazione cliente | G2: Allegato richiesto
A3: 1. | B3: Principi, obiettivi e strategie
B4: Sigla collaboratore capitolo 1:
A5: 1.1. | B5: Carta dei valori, principi direttivi
A6: 1.1.1. | C6: L'azienda ha una propria carta dei valori? | G6: 1.A
A7: 1.1.2. | C7: La sicurezza e la salute dei lavoratori fanno parte dei valori dell'azienda?
A8: 1.1.3. | C8: I dipendenti sono informati sull'importanza dei valori aziendali e sulle loro conseguenze nella vita di tutti i giorni?
A9: 1.1.4. | C9: Quanto avviene in azienda è in linea con la carta dei valori?
A10: 1.1.5. | C10: Il comportamento dei superiori si ispira a determinati principi o direttive? Se sì, quali?
A11: 1.1.6. | C11: La sicurezza e la tutela della salute sono menzionati tra i principi direttivi? | G11: 1.B
A12: 1.1.7. | C12: L'azienda ha firmato la Charta della sicurezza della Suva?
A13: 1.1.8.a | C13: Nell’azienda uno dei seguenti sistemi di gestione / certificazioni è in funzione? ISO 9001, ISO 14001, ISO 45001, OHSAS18001 Se sì, quale?
A14: 1.1.8.b | C14: Vengono introdotti altri sistemi di gestione / certificazioni? Se sì, quali?
A15: 1.2. | B15: Impegno della direzione
A16: 1.2.1. | C16: La sicurezza e la tutela della salute sono principi vissuti dalla direzione e vengono promossi con decisioni, regolamenti e direttive?
A17: 1.2.2. | C17: Nella vostra azienda, la sicurezza sul lavoro ha la stessa importanza della qualità e della produttività?
A18: 1.2.3. | C18: La direzione, durante le ispezioni in azienda, affronta le situazioni e i comportamenti pericolosi?
A19: 1.2.4. | C19: Per la sicurezza sul lavoro e la tutela della salute l'azienda ha conferito un centro costi?
A20: 1.2.5.a | C20: La direzione si impegna e appoggia le seguenti attività: Valutazioni dei rischi?
A21: 1.2.5.b | C21: Audit, controlli?
A22: 1.2.5.c | C22: Indagine d'infortunio?
A23: 1.2.5.d | C23: Formazioni sul posto di lavoro?
A24: 1.2.5.e | C24: Applicazione delle misure di sicurezza?
A25: 1.2.5.f | C25: Campagne per la sicurezza sul lavoro?
A26: 1.2.5.g | C26: Campagne per la sicurezza nel tempo libero?
A27: 1.2.5.h | C27: Gestione delle assenze?
A28: 1.2.5.i | C28: Altre? Se sì, quale?
A29: 1.3. | B29: Impegno dei superiori
A30: 1.3.1.a | C30: I superiori con il loro comportamento promuovono la sicurezza e la tutela della salute: Applicano per primi le norme di sicurezza (ad esempio usare i DPI)?
A31: 1.3.1.b | C31: Impongono il rispetto delle norme di sicurezza?
A32: 1.3.1.c | C32: Altri comportamenti e incentivi? Se sì, quali?
A33: 1.3.2.a | C33: Cosa fanno i superiori per promuovere la sicurezza e la tutela della salute sul lavoro? I superiori esercitano il proprio compito mediante: Valutazioni dei rischi?
A34: 1.3.2.b | C34: Audit, controlli?
A35: 1.3.2.c | C35: Indagine d'infortunio?
A36: 1.3.2.d | C36: Formazioni sul posto di lavoro?
A37: 1.3.2.e | C37: Campagne per la sicurezza sul lavoro?
A38: 1.3.2.f | C38: Campagne per la sicurezza nel tempo libero?
A39: 1.3.2.g | C39: Gestione delle assenze?
A40: 1.3.2.h | C40: Altre? Se sì, quale?
A41: 1.3.3 | C41: I superiori conoscono diritti e doveri stabiliti per legge in materia di sicurezza e tutela della salute?
A42: 1.4. | B42: Obiettivi di sicurezza
A43: 1.4.1.a | C43: Sono stati fissati obiettivi quantitativi per limitare la frequenza* degli eventi avversi e delle assenze: *Frequenza: Numero di eventi rispetto all'orario di lavoro produttivo o numero di eventi rispetto al numero degli occupati a tempo pieno in un determinato periodo. infortuni/malattie professionali? | G43: 1.C
A44: 1.4.1.b | C44: Infortuni non professionalki (INP)?
A45: 1.4.1.c | C45: Malattie?
A46: 1.4.1.d | C46: Danni materiali?
A47: 1.4.1.e | C47: Disturbi?
A48: 1.4.1.f | C48: Altri eventi? Se sì, quali eventi?
A49: 1.4.2.a | C49: Esistono obiettivi misurabili in termini di limitazione dei tempi di inattività causati dai seguenti eventi: infortuni/malattie professionali
A50: 1.4.2.b | C50: INP?
A51: 1.4.2.c | C51: Malattie?
A52: 1.4.2.d | C52: Altri eventi? Se sì, quali eventi?
A53: 1.4.3. | C53: Gli obiettivi per la sicurezza e la tutela della salute si riferiscono a tutta l'azienda?
A54: 1.4.4. | C54: Gli obiettivi per la sicurezza e la tutela della salute si riferiscono a singole unità organizzative?
A55: 1.4.5. | C55: Avete la possibilità di confrontare i dati della vostra azienda con quelli di altre aziende simili? Se sì, quali?
A56: 1.5. | B56: Formulazione degli obiettivi, controlling e strategia
A57: 1.5.1. | C57: Esiste un processo ben definito per formulare gli obiettivi di sicurezza?
A58: 1.5.2. | C58: Gli obiettivi prevedono anche l'obbligo del miglioramento continuo del sistema di sicurezza?
A59: 1.5.3. | C59: I quadri o i loro sostituti partecipano alla formulazione degli obiettivi di sicurezza?
A60: 1.5.4. | C60: Il mancato rispetto degli obiettivi viene riconosciuto tempestivamente con un esame attento degli eventi ossia con una procedura di controlling per tutta l'azienda?
A61: 1.5.5. | C61: per singole unità organizzative? (ad es. divisioni, settori)
A62: 1.5.6. | C62: In caso di mancato raggiungimento degli obiettivi si traggono le giuste conseguenze e si applicano le necessarie misure correttive? Se sì, quali conseguenze?
A63: 1.5.7. | C63: Avete una strategia per raggiungere gli obiettivi di sicurezza prefissi? (ad es. misure a medio termine, futuri trend, requisiti e aspettative di parti interessate) Se sì, quale?
A65: 2. | B65: Organizzazione
B66: Sigla collaboratore capitolo 2:
A67: 2.1. | B67: Organizzazione aziendale
A68: 2.1.1 | C68: Organisationsform
A69: 2.1.1.1.a | C69: Che tipo di organizzazione presenta la vostra azienda: Struttura in base alla linea? | G69: 2.A
A70: 2.1.1.2.b | C70: Struttura linea-staff?
A71: 2.1.1.2.c | C71: Struttura funzionale?
A72: 2.1.1.2.d | C72: Struttura a matrice?
A73: 2.1.1.2.e | C73: Struttura per progetto?
A74: 2.1.1.2.f | C74: Altro? Specificare
A75: 2.1.2. | C75: Compiti, competenze, responsabilità
A76: 2.1.2.1. | C76: Sono state messe per iscritto le competenze e le responsabilità in materia di sicurezza e tutela della salute?
A77: 2.1.2.2.a | C77: L'azienda dispone dei seguenti documenti organizzativi come; Descrizioni dei posti di lavoro? | G77: 2.B, 2.C, 2.D
A78: 2.1.2.2.b | C78: Mansionari?
A79: 2.1.2.2.c | C79: Diagrammi delle funzioni?
A80: 2.1.2.2.d | C80: Regolamenti? | G80: 2.E
A81: 2.1.2.2.e | C81: Contratti individuali di lavoro?
A82: 2.1.2.2.f | C82: Contratti collettivi?
A83: 2.1.2.2.g | C83: Contratti d'opera?
A84: 2.1.2.2.h | C84: Altro? Specificare
A85: 2.1.2.3.a | C85: I compiti, le competenze e le responsabilità (diritti e doveri) in materia di sicurezza e salute sono parte integrante dei seguenti documenti? Descrizioni dei posti di lavoro?
A86: 2.1.2.3.b | C86: Mansionari? | G86: 2.F
A87: 2.1.2.3.c | C87: Diagrammi delle funzioni?
A88: 2.1.2.3.d | C88: Regolamenti?
A89: 2.1.2.3.e | C89: Contratti individuali di lavoro?
A90: 2.1.2.3.f | C90: Contratti collettivi?
A91: 2.1.2.3.g | C91: Contratti d'opera?
A92: 2.1.2.3.h | C92: Altri documenti organizzativi?Specificare
A93: 2.1.3. | C93: Pianificazione e organizzazione del lavoro
A94: 2.1.3.1.a | C94: Chi svolge la pianificazione, il calcolo, l'organizzazione delle mansioni? Indicare tra i soggetti sotto indicati: superiori di linea?
A95: 2.1.3.1.b | C95: team di progetto?
A96: 2.1.3.1.c | C96: unità organizzativa creata ad hoc (preparazione dei lavori)
A97: 2.1.3.1.d | C97: Altri organi / persone? Se sì, quali organi / persone?
A98: 2.1.3.2. | C98: Nella fase di pianificazione, organizzazione, preparazione si tiene conto degli aspetti di sicurezza e tutela della salute?
... A103: 2.1.3.7. | C103: Gli incarichi vengono assegnati per iscritto e documentati?
A104: 2.1.3.8. | C104: Le direttive di lavoro in forma scritta riportano indicazioni sulle misure di sicurezza e di tutela della salute? | G104: 2.G
A105: 2.1.4. | C105: Regolamento aziendale
...

Sheet Allegati
A1: Allegati richiesti (se presenti) Vi preghiamo di inviarci gli allegati, se possibile, in formato PDF.
A2: N° Allegato | B2: Descrizione
A3: 1.A | B3: Carta di valori dell'azienda
A4: 1.B | B4: Principi direttivi dell'azienda
A5: 1.C | B5: Definizione scritta degli obiettivi di sicurezza dell'azienda
A6: 2.A | B6: Organigrammi dell'azienda
A7: 2.B | B7: Descrizione del lavoro per i superiori
A8: 2.C | B8: Descrizione del lavoro per posizione senza compiti dirigenziali
A9: 2.D | B9: Descrizione del lavoro per l'addetto alla sicurezza
A10: 2.E | B10: Regolamento del collaboratore aziendale
A11: 2.F | B11: Altri documenti riguardo compiti, doveri e responsabilità in materia di sicurezza e tutela della salute
A12: 2.G | B12: esempio di una istruzione di lavoro scritta
A13: 2.H | B13: Regolamento aziendale
... A43: 11.B | B43: Obiettivi, indicatori di performance della gestione delle assenze

Sheet Analyse
A1: Firma | B1: ='Dati aziendali'!C3 -> Muster AG | C1: Datum | E1: Nr.
A2: Analyse und Bewertung für Selbstbeuteilung und Ist-Aufnahme | C2: Antwort Kunde | F2: Interviewpartner | L2: Bewertung Suva | M2: Berechnung für Diagramm
C3: ja/nein (* keine Antwort) | D3: * | E3: Bemerkungen des Kunden | F3: GL | G3: Führung | H3: HR | I3: Si Org | J3: VG | K3: MA | L3: Erfüllungsgrad in Prozent | M3: Gewicht | N3: max Punktzahl | O3: Punkte Selbst | P3: Punkte Suva | Q3: Level 1 Selbst | R3: Level 1 Suva
A4: 1 | B4: =Autovalutazione!B3 -> Principi, obiettivi e strategie | C4: =O4/N4 -> 0 | L4: =P4/N4 -> 0 | N4: =SUM(M5,M15,M29,M42,M56) -> 17 | O4: =SUM(Q5:Q63) -> 0 | P4: =SUM(R5:R63) -> 0
A5: =Autovalutazione!A5 -> 1.1. | B5: =Autovalutazione!B5 -> Carta dei valori, principi direttivi | C5: =O5/N5 -> 0 | L5: =P5/N5 -> 0 | M5: 3 | N5: =SUM(M6:M14) -> 25 | O5: =SUM(O6:O14) -> 0 | P5: =SUM(P6:P14) -> 0 | Q5: =O5/$N5*$M5 -> 0 | R5: =P5/$N5*$M5 -> 0
A6: =Autovalutazione!A6 -> 1.1.1. | B6: =Autovalutazione!C6 -> L'azienda ha una propria carta dei valori? | C6: =IF(ISBLANK(Autovalutazione!D6),0,1) -> 0 | D6: =IF(AND(Autovalutazione!D6="",Autovalutazione!E6=""),"*","") -> * | E6: =IF(ISBLANK(Autovalutazione!F6),"",Autovalutazione!F6) | M6: 3 | O6: =C6*M6 -> 0 | P6: =L6*M6 -> 0
A7: =Autovalutazione!A7 -> 1.1.2. | B7: =Autovalutazione!C7 -> La sicurezza e la salute dei lavoratori fanno parte dei valori dell'azienda? | C7: =IF(ISBLANK(Autovalutazione!D7),0,1) -> 0 | D7: =IF(AND(Autovalutazione!D7="",Autovalutazione!E7=""),"*","") -> * | E7: =IF(ISBLANK(Autovalutazione!F7),"",Autovalutazione!F7) | M7: 4 | O7: =C7*M7 -> 0 | P7: =L7*M7 -> 0
A8: =Autovalutazione!A8 -> 1.1.3. | B8: =Autovalutazione!C8 -> I dipendenti sono informati sull'importanza dei valori aziendali e sulle loro conseguenze nella vita di tutti i giorni? | C8: =IF(ISBLANK(Autovalutazione!D8),0,1) -> 0 | D8: =IF(AND(Autovalutazione!D8="",Autovalutazione!E8=""),"*","") -> * | E8: =IF(ISBLANK(Autovalutazione!F8),"",Autovalutazione!F8) | M8: 5 | O8: =C8*M8 -> 0 | P8: =L8*M8 -> 0
A9: =Autovalutazione!A9 -> 1.1.4. | B9: =Autovalutazione!C9 -> Quanto avviene in azienda è in linea con la carta dei valori? | C9: =IF(ISBLANK(Autovalutazione!D9),0,1) -> 0 | D9: =IF(AND(Autovalutazione!D9="",Autovalutazione!E9=""),"*","") -> * | E9: =IF(ISBLANK(Autovalutazione!F9),"",Autovalutazione!F9) | M9: 5 | O9: =C9*M9 -> 0 | P9: =L9*M9 -> 0
A10: =Autovalutazione!A10 -> 1.1.5. | B10: =Autovalutazione!C10 -> Il comportamento dei superiori si ispira a determinati principi o direttive? Se sì, quali? | C10: =IF(ISBLANK(Autovalutazione!D10),0,1) -> 0 | D10: =IF(AND(Autovalutazione!D10="",Autovalutazione!E10=""),"*","") -> * | E10: =IF(ISBLANK(Autovalutazione!F10),"",Autovalutazione!F10) | M10: 0 | O10: =C10*M10 -> 0 | P10: =L10*M10 -> 0
A11: =Autovalutazione!A11 -> 1.1.6. | B11: =Autovalutazione!C11 -> La sicurezza e la tutela della salute sono menzionati tra i principi direttivi? | C11: =IF(ISBLANK(Autovalutazione!D11),0,1) -> 0 | D11: =IF(AND(Autovalutazione!D11="",Autovalutazione!E11=""),"*","") -> * | E11: =IF(ISBLANK(Autovalutazione!F11),"",Autovalutazione!F11) | M11: 3 | O11: =C11*M11 -> 0 | P11: =L11*M11 -> 0
A12: =Autovalutazione!A12 -> 1.1.7. | B12: =Autovalutazione!C12 -> L'azienda ha firmato la Charta della sicurezza della Suva? | C12: =IF(ISBLANK(Autovalutazione!D12),0,1) -> 0 | D12: =IF(AND(Autovalutazione!D12="",Autovalutazione!E12=""),"*","") -> * | E12: =IF(ISBLANK(Autovalutazione!F12),"",Autovalutazione!F12) | M12: 2 | O12: =C12*M12 -> 0 | P12: =L12*M12 -> 0
A13: =Autovalutazione!A13 -> 1.1.8.a | B13: =Autovalutazione!C13 -> Nell’azienda uno dei seguenti sistemi di gestione / certificazioni è in funzione? ISO 9001, ISO 14001, ISO 45001, OHSAS18001 Se sì, quale? | C13: =IF(ISBLANK(Autovalutazione!D13),0,1) -> 0 | D13: =IF(AND(Autovalutazione!D13="",Autovalutazione!E13=""),"*","") -> * | E13: =IF(ISBLANK(Autovalutazione!F13),"",Autovalutazione!F13) | M13: 3 | O13: =C13*M13 -> 0 | P13: =L13*M13 -> 0
A14: =Autovalutazione!A14 -> 1.1.8.b | B14: =Autovalutazione!C14 -> Vengono introdotti altri sistemi di gestione / certificazioni? Se sì, quali? | C14: =IF(ISBLANK(Autovalutazione!D14),0,1) -> 0 | D14: =IF(AND(Autovalutazione!D14="",Autovalutazione!E14=""),"*","") -> * | E14: =IF(ISBLANK(Autovalutazione!F14),"",Autovalutazione!F14) | M14: 0 | O14: =C14*M14 -> 0 | P14: =L14*M14 -> 0
A15: =Autovalutazione!A15 -> 1.2. | B15: =Autovalutazione!B15 -> Impegno della direzione | C15: =O15/N15 -> 0 | L15: =P15/N15 -> 0 | M15: 5 | N15: =SUM(M16:M28) -> 14 | O15: =SUM(O16:O28) -> 0 | P15: =SUM(P16:P28) -> 0 | Q15: =O15/$N15*$M15 -> 0 | R15: =P15/$N15*$M15 -> 0
A16: =Autovalutazione!A16 -> 1.2.1. | B16: =Autovalutazione!C16 -> La sicurezza e la tutela della salute sono principi vissuti dalla direzione e vengono promossi con decisioni, regolamenti e direttive? | C16: =IF(ISBLANK(Autovalutazione!D16),0,1) -> 0 | D16: =IF(AND(Autovalutazione!D16="",Autovalutazione!E16=""),"*","") -> * | E16: =IF(ISBLANK(Autovalutazione!F16),"",Autovalutazione!F16) | M16: 5 | O16: =M16*C16 -> 0 | P16: =L16*M16 -> 0
A17: =Autovalutazione!A17 -> 1.2.2. | B17: =Autovalutazione!C17 -> Nella vostra azienda, la sicurezza sul lavoro ha la stessa importanza della qualità e della produttività? | C17: =IF(ISBLANK(Autovalutazione!D17),0,1) -> 0 | D17: =IF(AND(Autovalutazione!D17="",Autovalutazione!E17=""),"*","") -> * | E17: =IF(ISBLANK(Autovalutazione!F17),"",Autovalutazione!F17) | M17: 5 | O17: =M17*C17 -> 0 | P17: =L17*M17 -> 0
A18: =Autovalutazione!A18 -> 1.2.3. | B18: =Autovalutazione!C18 -> La direzione, durante le ispezioni in azienda, affronta le situazioni e i comportamenti pericolosi? | C18: =IF(ISBLANK(Autovalutazione!D18),0,1) -> 0 | D18: =IF(AND(Autovalutazione!D18="",Autovalutazione!E18=""),"*","") -> * | E18: =IF(ISBLANK(Autovalutazione!F18),"",Autovalutazione!F18) | M18: 3 | O18: =M18*C18 -> 0 | P18: =L18*M18 -> 0
A19: =Autovalutazione!A19 -> 1.2.4. | B19: =Autovalutazione!C19 -> Per la sicurezza sul lavoro e la tutela della salute l'azienda ha conferito un centro costi? | C19: =IF(ISBLANK(Autovalutazione!D19),0,1) -> 0 | D19: =IF(AND(Autovalutazione!D19="",Autovalutazione!E19=""),"*","") -> * | E19: =IF(ISBLANK(Autovalutazione!F19),"",Autovalutazione!F19) | M19: 1 | O19: =M19*C19 -> 0 | P19: =L19*M19 -> 0
A20: =Autovalutazione!A20 -> 1.2.5.a | B20: =Autovalutazione!C20 -> La direzione si impegna e appoggia le seguenti attività: Valutazioni dei rischi? | C20: =IF(ISBLANK(Autovalutazione!D20),0,1) -> 0 | D20: =IF(AND(Autovalutazione!D20="",Autovalutazione!E20=""),"*","") -> * | E20: =IF(ISBLANK(Autovalutazione!F20),"",Autovalutazione!F20) | M20: 0 | O20: =M20*C20 -> 0 | P20: =L20*M20 -> 0
A21: =Autovalutazione!A21 -> 1.2.5.b | B21: =Autovalutazione!C21 -> Audit, controlli? | C21: =IF(ISBLANK(Autovalutazione!D21),0,1) -> 0 | D21: =IF(AND(Autovalutazione!D21="",Autovalutazione!E21=""),"*","") -> * | E21: =IF(ISBLANK(Autovalutazione!F21),"",Autovalutazione!F21) | M21: 0 | O21: =M21*C21 -> 0 | P21: =L21*M21 -> 0
A22: =Autovalutazione!A22 -> 1.2.5.c | B22: =Autovalutazione!C22 -> Indagine d'infortunio? | C22: =IF(ISBLANK(Autovalutazione!D22),0,1) -> 0 | D22: =IF(AND(Autovalutazione!D22="",Autovalutazione!E22=""),"*","") -> * | E22: =IF(ISBLANK(Autovalutazione!F22),"",Autovalutazione!F22) | M22: 0 | O22: =M22*C22 -> 0 | P22: =L22*M22 -> 0
A23: =Autovalutazione!A23 -> 1.2.5.d | B23: =Autovalutazione!C23 -> Formazioni sul posto di lavoro? | C23: =IF(ISBLANK(Autovalutazione!D23),0,1) -> 0 | D23: =IF(AND(Autovalutazione!D23="",Autovalutazione!E23=""),"*","") -> * | E23: =IF(ISBLANK(Autovalutazione!F23),"",Autovalutazione!F23) | M23: 0 | O23: =M23*C23 -> 0 | P23: =L23*M23 -> 0
A24: =Autovalutazione!A24 -> 1.2.5.e | B24: =Autovalutazione!C24 -> Applicazione delle misure di sicurezza? | C24: =IF(ISBLANK(Autovalutazione!D24),0,1) -> 0 | D24: =IF(AND(Autovalutazione!D24="",Autovalutazione!E24=""),"*","") -> * | E24: =IF(ISBLANK(Autovalutazione!F24),"",Autovalutazione!F24) | M24: 0 | O24: =M24*C24 -> 0 | P24: =L24*M24 -> 0
A25: =Autovalutazione!A25 -> 1.2.5.f | B25: =Autovalutazione!C25 -> Campagne per la sicurezza sul lavoro? | C25: =IF(ISBLANK(Autovalutazione!D25),0,1) -> 0 | D25: =IF(AND(Autovalutazione!D25="",Autovalutazione!E25=""),"*","") -> * | E25: =IF(ISBLANK(Autovalutazione!F25),"",Autovalutazione!F25) | M25: 0 | O25: =M25*C25 -> 0 | P25: =L25*M25 -> 0
A26: =Autovalutazione!A26 -> 1.2.5.g | B26: =Autovalutazione!C26 -> Campagne per la sicurezza nel tempo libero? | C26: =IF(ISBLANK(Autovalutazione!D26),0,1) -> 0 | D26: =IF(AND(Autovalutazione!D26="",Autovalutazione!E26=""),"*","") -> * | E26: =IF(ISBLANK(Autovalutazione!F26),"",Autovalutazione!F26) | M26: 0 | O26: =M26*C26 -> 0 | P26: =L26*M26 -> 0
A27: =Autovalutazione!A27 -> 1.2.5.h | B27: =Autovalutazione!C27 -> Gestione delle assenze? | C27: =IF(ISBLANK(Autovalutazione!D27),0,1) -> 0 | D27: =IF(AND(Autovalutazione!D27="",Autovalutazione!E27=""),"*","") -> * | E27: =IF(ISBLANK(Autovalutazione!F27),"",Autovalutazione!F27) | M27: 0 | O27: =M27*C27 -> 0 | P27: =L27*M27 -> 0
A28: =Autovalutazione!A28 -> 1.2.5.i | B28: =Autovalutazione!C28 -> Altre? Se sì, quale? | C28: =IF(ISBLANK(Autovalutazione!D28),0,1) -> 0 | D28: =IF(AND(Autovalutazione!D28="",Autovalutazione!E28=""),"*","") -> * | E28: =IF(ISBLANK(Autovalutazione!F28),"",Autovalutazione!F28) | M28: 0 | O28: =M28*C28 -> 0 | P28: =L28*M28 -> 0
A29: =Autovalutazione!A29 -> 1.3. | B29: =Autovalutazione!B29 -> Impegno dei superiori | C29: =O29/N29 -> 0 | L29: =P29/N29 -> 0 | M29: 5 | N29: =SUM(M30:M41) -> 21 | O29: =SUM(O30:O41) -> 0 | P29: =SUM(P30:P41) -> 0 | Q29: =O29/$N29*$M29 -> 0 | R29: =P29/$N29*$M29 -> 0
A30: =Autovalutazione!A30 -> 1.3.1.a | B30: =Autovalutazione!C30 -> I superiori con il loro comportamento promuovono la sicurezza e la tutela della salute: Applicano per primi le norme di sicurezza (ad esempio usare i DPI)? | C30: =IF(ISBLANK(Autovalutazione!D30),0,1) -> 0 | D30: =IF(AND(Autovalutazione!D30="",Autovalutazione!E30=""),"*","") -> * | E30: =IF(ISBLANK(Autovalutazione!F30),"",Autovalutazione!F30) | M30: 5 | O30: =M30*C30 -> 0 | P30: =L30*M30 -> 0
A31: =Autovalutazione!A31 -> 1.3.1.b | B31: =Autovalutazione!C31 -> Impongono il rispetto delle norme di sicurezza? | C31: =IF(ISBLANK(Autovalutazione!D31),0,1) -> 0 | D31: =IF(AND(Autovalutazione!D31="",Autovalutazione!E31=""),"*","") -> * | E31: =IF(ISBLANK(Autovalutazione!F31),"",Autovalutazione!F31) | M31: 5 | O31: =M31*C31 -> 0 | P31: =L31*M31 -> 0
A32: =Autovalutazione!A32 -> 1.3.1.c | B32: =Autovalutazione!C32 -> Altri comportamenti e incentivi? Se sì, quali? | C32: =IF(ISBLANK(Autovalutazione!D32),0,1) -> 0 | D32: =IF(AND(Autovalutazione!D32="",Autovalutazione!E32=""),"*","") -> * | E32: =IF(ISBLANK(Autovalutazione!F32),"",Autovalutazione!F32) | M32: 0 | O32: =M32*C32 -> 0 | P32: =L32*M32 -> 0
A33: =Autovalutazione!A33 -> 1.3.2.a | B33: =Autovalutazione!C33 -> Cosa fanno i superiori per promuovere la sicurezza e la tutela della salute sul lavoro? I superiori esercitano il proprio compito mediante: Valutazioni dei rischi? | C33: =IF(ISBLANK(Autovalutazione!D33),0,1) -> 0 | D33: =IF(AND(Autovalutazione!D33="",Autovalutazione!E33=""),"*","") -> * | E33: =IF(ISBLANK(Autovalutazione!F33),"",Autovalutazione!F33) | M33: 0 | O33: =M33*C33 -> 0 | P33: =L33*M33 -> 0
A34: =Autovalutazione!A34 -> 1.3.2.b | B34: =Autovalutazione!C34 -> Audit, controlli? | C34: =IF(ISBLANK(Autovalutazione!D34),0,1) -> 0 | D34: =IF(AND(Autovalutazione!D34="",Autovalutazione!E34=""),"*","") -> * | E34: =IF(ISBLANK(Autovalutazione!F34),"",Autovalutazione!F34) | M34: 2 | O34: =M34*C34 -> 0 | P34: =L34*M34 -> 0
A35: =Autovalutazione!A35 -> 1.3.2.c | B35: =Autovalutazione!C35 -> Indagine d'infortunio? | C35: =IF(ISBLANK(Autovalutazione!D35),0,1) -> 0 | D35: =IF(AND(Autovalutazione!D35="",Autovalutazione!E35=""),"*","") -> * | E35: =IF(ISBLANK(Autovalutazione!F35),"",Autovalutazione!F35) | M35: 2 | O35: =M35*C35 -> 0 | P35: =L35*M35 -> 0
A36: =Autovalutazione!A36 -> 1.3.2.d | B36: =Autovalutazione!C36 -> Formazioni sul posto di lavoro? | C36: =IF(ISBLANK(Autovalutazione!D36),0,1) -> 0 | D36: =IF(AND(Autovalutazione!D36="",Autovalutazione!E36=""),"*","") -> * | E36: =IF(ISBLANK(Autovalutazione!F36),"",Autovalutazione!F36) | M36: 2 | O36: =M36*C36 -> 0 | P36: =L36*M36 -> 0
A37: =Autovalutazione!A37 -> 1.3.2.e | B37: =Autovalutazione!C37 -> Campagne per la sicurezza sul lavoro? | C37: =IF(ISBLANK(Autovalutazione!D37),0,1) -> 0 | D37: =IF(AND(Autovalutazione!D37="",Autovalutazione!E37=""),"*","") -> * | E37: =IF(ISBLANK(Autovalutazione!F37),"",Autovalutazione!F37) | M37: 0 | O37: =M37*C37 -> 0 | P37: =L37*M37 -> 0
A38: =Autovalutazione!A38 -> 1.3.2.f | B38: =Autovalutazione!C38 -> Campagne per la sicurezza nel tempo libero? | C38: =IF(ISBLANK(Autovalutazione!D38),0,1) -> 0 | D38: =IF(AND(Autovalutazione!D38="",Autovalutazione!E38=""),"*","") -> * | E38: =IF(ISBLANK(Autovalutazione!F38),"",Autovalutazione!F38) | M38: 0 | O38: =M38*C38 -> 0 | P38: =L38*M38 -> 0
A39: =Autovalutazione!A39 -> 1.3.2.g | B39: =Autovalutazione!C39 -> Gestione delle assenze? | C39: =IF(ISBLANK(Autovalutazione!D39),0,1) -> 0 | D39: =IF(AND(Autovalutazione!D39="",Autovalutazione!E39=""),"*","") -> * | E39: =IF(ISBLANK(Autovalutazione!F39),"",Autovalutazione!F39) | M39: 2 | O39: =M39*C39 -> 0 | P39: =L39*M39 -> 0
A40: =Autovalutazione!A40 -> 1.3.2.h | B40: =Autovalutazione!C40 -> Altre? Se sì, quale? | C40: =IF(ISBLANK(Autovalutazione!D40),0,1) -> 0 | D40: =IF(AND(Autovalutazione!D40="",Autovalutazione!E40=""),"*","") -> * | E40: =IF(ISBLANK(Autovalutazione!F40),"",Autovalutazione!F40) | M40: 0 | O40: =M40*C40 -> 0 | P40: =L40*M40 -> 0
A41: =Autovalutazione!A41 -> 1.3.3 | B41: =Autovalutazione!C41 -> I superiori conoscono diritti e doveri stabiliti per legge in materia di sicurezza e tutela della salute? | C41: =IF(ISBLANK(Autovalutazione!D41),0,1) -> 0 | D41: =IF(AND(Autovalutazione!D41="",Autovalutazione!E41=""),"*","") -> * | E41: =IF(ISBLANK(Autovalutazione!F41),"",Autovalutazione!F41) | M41: 3 | O41: =M41*C41 -> 0 | P41: =L41*M41 -> 0
A42: =Autovalutazione!A42 -> 1.4. | B42: =Autovalutazione!B42 -> Obiettivi di sicurezza | C42: =O42/N42 -> 0 | L42: =P42/N42 -> 0 | M42: 2 | N42: =SUM(M43:M55) -> 21 | O42: =SUM(O43:O55) -> 0 | P42: =SUM(P43:P55) -> 0 | Q42: =O42/$N42*$M42 -> 0 | R42: =P42/$N42*$M42 -> 0
A43: =Autovalutazione!A43 -> 1.4.1.a | B43: =Autovalutazione!C43 -> Sono stati fissati obiettivi quantitativi per limitare la frequenza* degli eventi avversi e delle assenze: *Frequenza: Numero di eventi rispetto all'orario di lavoro produttivo o numero di eventi rispetto al numero degli occupati a tempo pieno in un determinato periodo. infortuni/malattie professionali? | C43: =IF(ISBLANK(Autovalutazione!D43),0,1) -> 0 | D43: =IF(AND(Autovalutazione!D43="",Autovalutazione!E43=""),"*","") -> * | E43: =IF(ISBLANK(Autovalutazione!F43),"",Autovalutazione!F43) | M43: 5 | O43: =M43*C43 -> 0 | P43: =L43*M43 -> 0
A44: =Autovalutazione!A44 -> 1.4.1.b | B44: =Autovalutazione!C44 -> Infortuni non professionalki (INP)? | C44: =IF(ISBLANK(Autovalutazione!D44),0,1) -> 0 | D44: =IF(AND(Autovalutazione!D44="",Autovalutazione!E44=""),"*","") -> * | E44: =IF(ISBLANK(Autovalutazione!F44),"",Autovalutazione!F44) | M44: 3 | O44: =M44*C44 -> 0 | P44: =L44*M44 -> 0
A45: =Autovalutazione!A45 -> 1.4.1.c | B45: =Autovalutazione!C45 -> Malattie? | C45: =IF(ISBLANK(Autovalutazione!D45),0,1) -> 0 | D45: =IF(AND(Autovalutazione!D45="",Autovalutazione!E45=""),"*","") -> * | E45: =IF(ISBLANK(Autovalutazione!F45),"",Autovalutazione!F45) | M45: 2 | O45: =M45*C45 -> 0 | P45: =L45*M45 -> 0
A46: =Autovalutazione!A46 -> 1.4.1.d | B46: =Autovalutazione!C46 -> Danni materiali? | C46: =IF(ISBLANK(Autovalutazione!D46),0,1) -> 0 | D46: =IF(AND(Autovalutazione!D46="",Autovalutazione!E46=""),"*","") -> * | E46: =IF(ISBLANK(Autovalutazione!F46),"",Autovalutazione!F46) | M46: 3 | O46: =M46*C46 -> 0 | P46: =L46*M46 -> 0
A47: =Autovalutazione!A47 -> 1.4.1.e | B47: =Autovalutazione!C47 -> Disturbi? | C47: =IF(ISBLANK(Autovalutazione!D47),0,1) -> 0 | D47: =IF(AND(Autovalutazione!D47="",Autovalutazione!E47=""),"*","") -> * | E47: =IF(ISBLANK(Autovalutazione!F47),"",Autovalutazione!F47) | M47: 0 | O47: =M47*C47 -> 0 | P47: =L47*M47 -> 0
A48: =Autovalutazione!A48 -> 1.4.1.f | B48: =Autovalutazione!C48 -> Altri eventi? Se sì, quali eventi? | C48: =IF(ISBLANK(Autovalutazione!D48),0,1) -> 0 | D48: =IF(AND(Autovalutazione!D48="",Autovalutazione!E48=""),"*","") -> * | E48: =IF(ISBLANK(Autovalutazione!F48),"",Autovalutazione!F48) | M48: 0 | O48: =M48*C48 -> 0 | P48: =L48*M48 -> 0
A49: =Autovalutazione!A49 -> 1.4.2.a | B49: =Autovalutazione!C49 -> Esistono obiettivi misurabili in termini di limitazione dei tempi di inattività causati dai seguenti eventi: infortuni/malattie professionali | C49: =IF(ISBLANK(Autovalutazione!D49),0,1) -> 0 | D49: =IF(AND(Autovalutazione!D49="",Autovalutazione!E49=""),"*","") -> * | E49: =IF(ISBLANK(Autovalutazione!F49),"",Autovalutazione!F49) | M49: 1 | O49: =M49*C49 -> 0 | P49: =L49*M49 -> 0
A50: =Autovalutazione!A50 -> 1.4.2.b | B50: =Autovalutazione!C50 -> INP? | C50: =IF(ISBLANK(Autovalutazione!D50),0,1) -> 0 | D50: =IF(AND(Autovalutazione!D50="",Autovalutazione!E50=""),"*","") -> * | E50: =IF(ISBLANK(Autovalutazione!F50),"",Autovalutazione!F50) | M50: 1 | O50: =M50*C50 -> 0 | P50: =L50*M50 -> 0
A51: =Autovalutazione!A51 -> 1.4.2.c | B51: =Autovalutazione!C51 -> Malattie? | C51: =IF(ISBLANK(Autovalutazione!D51),0,1) -> 0 | D51: =IF(AND(Autovalutazione!D51="",Autovalutazione!E51=""),"*","") -> * | E51: =IF(ISBLANK(Autovalutazione!F51),"",Autovalutazione!F51) | M51: 3 | O51: =M51*C51 -> 0 | P51: =L51*M51 -> 0
A52: =Autovalutazione!A52 -> 1.4.2.d | B52: =Autovalutazione!C52 -> Altri eventi? Se sì, quali eventi? | C52: =IF(ISBLANK(Autovalutazione!D52),0,1) -> 0 | D52: =IF(AND(Autovalutazione!D52="",Autovalutazione!E52=""),"*","") -> * | E52: =IF(ISBLANK(Autovalutazione!F52),"",Autovalutazione!F52) | M52: 0 | O52: =M52*C52 -> 0 | P52: =L52*M52 -> 0
A53: =Autovalutazione!A53 -> 1.4.3. | B53: =Autovalutazione!C53 -> Gli obiettivi per la sicurezza e la tutela della salute si riferiscono a tutta l'azienda? | C53: =IF(ISBLANK(Autovalutazione!D53),0,1) -> 0 | D53: =IF(AND(Autovalutazione!D53="",Autovalutazione!E53=""),"*","") -> * | E53: =IF(ISBLANK(Autovalutazione!F53),"",Autovalutazione!F53) | M53: 1 | O53: =M53*C53 -> 0 | P53: =L53*M53 -> 0
A54: =Autovalutazione!A54 -> 1.4.4. | B54: =Autovalutazione!C54 -> Gli obiettivi per la sicurezza e la tutela della salute si riferiscono a singole unità organizzative? | C54: =IF(ISBLANK(Autovalutazione!D54),0,1) -> 0 | D54: =IF(AND(Autovalutazione!D54="",Autovalutazione!E54=""),"*","") -> * | E54: =IF(ISBLANK(Autovalutazione!F54),"",Autovalutazione!F54) | M54: 1 | O54: =M54*C54 -> 0 | P54: =L54*M54 -> 0
A55: =Autovalutazione!A55 -> 1.4.5. | B55: =Autovalutazione!C55 -> Avete la possibilità di confrontare i dati della vostra azienda con quelli di altre aziende simili? Se sì, quali? | C55: =IF(ISBLANK(Autovalutazione!D55),0,1) -> 0 | D55: =IF(AND(Autovalutazione!D55="",Autovalutazione!E55=""),"*","") -> * | E55: =IF(ISBLANK(Autovalutazione!F55),"",Autovalutazione!F55) | M55: 1 | O55: =M55*C55 -> 0 | P55: =L55*M55 -> 0
A56: =Autovalutazione!A56 -> 1.5. | B56: =Autovalutazione!B56 -> Formulazione degli obiettivi, controlling e strategia | C56: =O56/N56 -> 0 | L56: =P56/N56 -> 0 | M56: 2 | N56: =SUM(M57:M63) -> 17 | O56: =SUM(O57:O63) -> 0 | P56: =SUM(P57:P63) -> 0 | Q56: =O56/$N56*$M56 -> 0 | R56: =P56/$N56*$M56 -> 0
A57: =Autovalutazione!A57 -> 1.5.1. | B57: =Autovalutazione!C57 -> Esiste un processo ben definito per formulare gli obiettivi di sicurezza? | C57: =IF(ISBLANK(Autovalutazione!D57),0,1) -> 0 | D57: =IF(AND(Autovalutazione!D57="",Autovalutazione!E57=""),"*","") -> * | E57: =IF(ISBLANK(Autovalutazione!F57),"",Autovalutazione!F57) | M57: 3 | O57: =M57*C57 -> 0 | P57: =L57*M57 -> 0
A58: =Autovalutazione!A58 -> 1.5.2. | B58: =Autovalutazione!C58 -> Gli obiettivi prevedono anche l'obbligo del miglioramento continuo del sistema di sicurezza? | C58: =IF(ISBLANK(Autovalutazione!D58),0,1) -> 0 | D58: =IF(AND(Autovalutazione!D58="",Autovalutazione!E58=""),"*","") -> * | E58: =IF(ISBLANK(Autovalutazione!F58),"",Autovalutazione!F58) | M58: 3 | O58: =M58*C58 -> 0 | P58: =L58*M58 -> 0
A59: =Autovalutazione!A59 -> 1.5.3. | B59: =Autovalutazione!C59 -> I quadri o i loro sostituti partecipano alla formulazione degli obiettivi di sicurezza? | C59: =IF(ISBLANK(Autovalutazione!D59),0,1) -> 0 | D59: =IF(AND(Autovalutazione!D59="",Autovalutazione!E59=""),"*","") -> * | E59: =IF(ISBLANK(Autovalutazione!F59),"",Autovalutazione!F59) | M59: 4 | O59: =M59*C59 -> 0 | P59: =L59*M59 -> 0
A60: =Autovalutazione!A60 -> 1.5.4. | B60: =Autovalutazione!C60 -> Il mancato rispetto degli obiettivi viene riconosciuto tempestivamente con un esame attento degli eventi ossia con una procedura di controlling per tutta l'azienda? | C60: =IF(ISBLANK(Autovalutazione!D60),0,1) -> 0 | D60: =IF(AND(Autovalutazione!D60="",Autovalutazione!E60=""),"*","") -> * | E60: =IF(ISBLANK(Autovalutazione!F60),"",Autovalutazione!F60) | M60: 1 | O60: =M60*C60 -> 0 | P60: =L60*M60 -> 0
A61: =Autovalutazione!A61 -> 1.5.5. | B61: =Autovalutazione!C61 -> per singole unità organizzative? (ad es. divisioni, settori) | C61: =IF(ISBLANK(Autovalutazione!D61),0,1) -> 0 | D61: =IF(AND(Autovalutazione!D61="",Autovalutazione!E61=""),"*","") -> * | E61: =IF(ISBLANK(Autovalutazione!F61),"",Autovalutazione!F61) | M61: 1 | O61: =M61*C61 -> 0 | P61: =L61*M61 -> 0
A62: =Autovalutazione!A62 -> 1.5.6. | B62: =Autovalutazione!C62 -> In caso di mancato raggiungimento degli obiettivi si traggono le giuste conseguenze e si applicano le necessarie misure correttive? Se sì, quali conseguenze? | C62: =IF(ISBLANK(Autovalutazione!D62),0,1) -> 0 | D62: =IF(AND(Autovalutazione!D62="",Autovalutazione!E62=""),"*","") -> * | E62: =IF(ISBLANK(Autovalutazione!F62),"",Autovalutazione!F62) | M62: 3 | O62: =M62*C62 -> 0 | P62: =L62*M62 -> 0
A63: =Autovalutazione!A63 -> 1.5.7. | B63: =Autovalutazione!C63 -> Avete una strategia per raggiungere gli obiettivi di sicurezza prefissi? (ad es. misure a medio termine, futuri trend, requisiti e aspettative di parti interessate) Se sì, quale? | C63: =IF(ISBLANK(Autovalutazione!D63),0,1) -> 0 | D63: =IF(AND(Autovalutazione!D63="",Autovalutazione!E63=""),"*","") -> * | E63: =IF(ISBLANK(Autovalutazione!F63),"",Autovalutazione!F63) | M63: 2 | O63: =M63*C63 -> 0 | P63: =L63*M63 -> 0
A64: =Autovalutazione!A65 -> 2. | B64: =Autovalutazione!B65 -> Organizzazione | C64: =O64/N64 -> 0 | L64: =P64/N64 -> 0 | N64: =SUM(M65,M106,M127) -> 7 | O64: =SUM(Q65,Q106,Q127) -> 0 | P64: =SUM(R65,R106,R127) -> 0
A65: =Autovalutazione!A67 -> 2.1. | B65: =Autovalutazione!B67 -> Organizzazione aziendale | C65: =O65/N65 -> 0 | D65: =IF(ISBLANK(Autovalutazione!E67),"",Autovalutazione!E67) | L65: =P65/N65 -> 0 | M65: 3 | N65: =SUM(M66,M73,M91,M103) -> 7 | O65: =SUM(Q66,Q73,Q91,Q103) -> 0 | P65: =SUM(R66,R73,R91,R103) -> 0 | Q65: =O65/$N65*$M65 -> 0 | R65: =P65/$N65*$M65 -> 0
A66: =Autovalutazione!A68 -> 2.1.1 | B66: =Autovalutazione!C68 -> Organisationsform | C66: =O66/N66 -> 0 | D66: =IF(ISBLANK(Autovalutazione!E68),"",Autovalutazione!E68) | L66: =P66/N66 -> 0 | M66: 1 | N66: =MAX(M67:M72) -> 1 | O66: =MAX(O67:O72) -> 0 | P66: =MAX(P67:P72) -> 0 | Q66: =O66/N66*M66 -> 0 | R66: =P66/N66*$M66 -> 0
A67: =Autovalutazione!A69 -> 2.1.1.1.a | B67: =Autovalutazione!C69 -> Che tipo di organizzazione presenta la vostra azienda: Struttura in base alla linea? | C67: =IF(ISBLANK(Autovalutazione!D69),0,1) -> 0 | D67: =IF(AND(Autovalutazione!D69="",Autovalutazione!E69=""),"*","") -> * | E67: =IF(ISBLANK(Autovalutazione!F69),"",Autovalutazione!F69) | M67: 1 | O67: =C67*M67 -> 0 | P67: =L67*M67 -> 0
A68: =Autovalutazione!A70 -> 2.1.1.2.b | B68: =Autovalutazione!C70 -> Struttura linea-staff? | C68: =IF(ISBLANK(Autovalutazione!D70),0,1) -> 0 | D68: =IF(AND(Autovalutazione!D70="",Autovalutazione!E70=""),"*","") -> * | E68: =IF(ISBLANK(Autovalutazione!F70),"",Autovalutazione!F70) | M68: 1 | O68: =C68*M68 -> 0 | P68: =L68*M68 -> 0
A69: =Autovalutazione!A71 -> 2.1.1.2.c | B69: =Autovalutazione!C71 -> Struttura funzionale? | C69: =IF(ISBLANK(Autovalutazione!D71),0,1) -> 0 | D69: =IF(AND(Autovalutazione!D71="",Autovalutazione!E71=""),"*","") -> * | E69: =IF(ISBLANK(Autovalutazione!F71),"",Autovalutazione!F71) | M69: 1 | O69: =C69*M69 -> 0 | P69: =L69*M69 -> 0
A70: =Autovalutazione!A72 -> 2.1.1.2.d | B70: =Autovalutazione!C72 -> Struttura a matrice? | C70: =IF(ISBLANK(Autovalutazione!D72),0,1) -> 0 | D70: =IF(AND(Autovalutazione!D72="",Autovalutazione!E72=""),"*","") -> * | E70: =IF(ISBLANK(Autovalutazione!F72),"",Autovalutazione!F72) | M70: 1 | O70: =C70*M70 -> 0 | P70: =L70*M70 -> 0
A71: =Autovalutazione!A73 -> 2.1.1.2.e | B71: =Autovalutazione!C73 -> Struttura per progetto? | C71: =IF(ISBLANK(Autovalutazione!D73),0,1) -> 0 | D71: =IF(AND(Autovalutazione!D73="",Autovalutazione!E73=""),"*","") -> * | E71: =IF(ISBLANK(Autovalutazione!F73),"",Autovalutazione!F73) | M71: 1 | O71: =C71*M71 -> 0 | P71: =L71*M71 -> 0
A72: =Autovalutazione!A74 -> 2.1.1.2.f | B72: =Autovalutazione!C74 -> Altro? Specificare | C72: =IF(ISBLANK(Autovalutazione!D74),0,1) -> 0 | D72: =IF(AND(Autovalutazione!D74="",Autovalutazione!E74=""),"*","") -> * | E72: =IF(ISBLANK(Autovalutazione!F74),"",Autovalutazione!F74) | M72: 1 | O72: =C72*M72 -> 0 | P72: =L72*M72 -> 0
A73: =Autovalutazione!A75 -> 2.1.2. | B73: =Autovalutazione!C75 -> Compiti, competenze, responsabilità | C73: =O73/N73 -> 0 | D73: =IF(ISBLANK(Autovalutazione!E75),"",Autovalutazione!E75) | E73: =IF(ISBLANK(Autovalutazione!F75),"",Autovalutazione!F75) | L73: =P73/N73 -> 0 | M73: 3 | N73: =SUM(M74:M90) -> 21 | O73: =SUM(O74:O90) -> 0 | P73: =SUM(P74:P90) -> 0 | Q73: =O73/$N73*$M73 -> 0 | R73: =P73/$N73*$M73 -> 0
A74: =Autovalutazione!A76 -> 2.1.2.1. | B74: =Autovalutazione!C76 -> Sono state messe per iscritto le competenze e le responsabilità in materia di sicurezza e tutela della salute? | C74: =IF(ISBLANK(Autovalutazione!D76),0,1) -> 0 | D74: =IF(AND(Autovalutazione!D76="",Autovalutazione!E76=""),"*","") -> * | E74: =IF(ISBLANK(Autovalutazione!F76),"",Autovalutazione!F76) | M74: 4 | O74: =C74*M74 -> 0 | P74: =L74*M74 -> 0
A75: =Autovalutazione!A77 -> 2.1.2.2.a | B75: =Autovalutazione!C77 -> L'azienda dispone dei seguenti documenti organizzativi come; Descrizioni dei posti di lavoro? | C75: =IF(ISBLANK(Autovalutazione!D77),0,1) -> 0 | D75: =IF(AND(Autovalutazione!D77="",Autovalutazione!E77=""),"*","") -> * | E75: =IF(ISBLANK(Autovalutazione!F77),"",Autovalutazione!F77) | M75: 2 | O75: =C75*M75 -> 0 | P75: =L75*M75 -> 0
A76: =Autovalutazione!A78 -> 2.1.2.2.b | B76: =Autovalutazione!C78 -> Mansionari? | C76: =IF(ISBLANK(Autovalutazione!D78),0,1) -> 0 | D76: =IF(AND(Autovalutazione!D78="",Autovalutazione!E78=""),"*","") -> * | E76: =IF(ISBLANK(Autovalutazione!F78),"",Autovalutazione!F78) | M76: 1 | O76: =C76*M76 -> 0 | P76: =L76*M76 -> 0
A77: =Autovalutazione!A79 -> 2.1.2.2.c | B77: =Autovalutazione!C79 -> Diagrammi delle funzioni? | C77: =IF(ISBLANK(Autovalutazione!D79),0,1) -> 0 | D77: =IF(AND(Autovalutazione!D79="",Autovalutazione!E79=""),"*","") -> * | E77: =IF(ISBLANK(Autovalutazione!F79),"",Autovalutazione!F79) | M77: 0 | O77: =C77*M77 -> 0 | P77: =L77*M77 -> 0
A78: =Autovalutazione!A80 -> 2.1.2.2.d | B78: =Autovalutazione!C80 -> Regolamenti? | C78: =IF(ISBLANK(Autovalutazione!D80),0,1) -> 0 | D78: =IF(AND(Autovalutazione!D80="",Autovalutazione!E80=""),"*","") -> * | E78: =IF(ISBLANK(Autovalutazione!F80),"",Autovalutazione!F80) | M78: 2 | O78: =C78*M78 -> 0 | P78: =L78*M78 -> 0
A79: =Autovalutazione!A81 -> 2.1.2.2.e | B79: =Autovalutazione!C81 -> Contratti individuali di lavoro? | C79: =IF(ISBLANK(Autovalutazione!D81),0,1) -> 0 | D79: =IF(AND(Autovalutazione!D81="",Autovalutazione!E81=""),"*","") -> * | E79: =IF(ISBLANK(Autovalutazione!F81),"",Autovalutazione!F81) | M79: 2 | O79: =C79*M79 -> 0 | P79: =L79*M79 -> 0
A80: =Autovalutazione!A82 -> 2.1.2.2.f | B80: =Autovalutazione!C82 -> Contratti collettivi? | C80: =IF(ISBLANK(Autovalutazione!D82),0,1) -> 0 | D80: =IF(AND(Autovalutazione!D82="",Autovalutazione!E82=""),"*","") -> * | E80: =IF(ISBLANK(Autovalutazione!F82),"",Autovalutazione!F82) | M80: 0 | O80: =C80*M80 -> 0 | P80: =L80*M80 -> 0
A81: =Autovalutazione!A83 -> 2.1.2.2.g | B81: =Autovalutazione!C83 -> Contratti d'opera? | C81: =IF(ISBLANK(Autovalutazione!D83),0,1) -> 0 | D81: =IF(AND(Autovalutazione!D83="",Autovalutazione!E83=""),"*","") -> * | E81: =IF(ISBLANK(Autovalutazione!F83),"",Autovalutazione!F83) | M81: 1 | O81: =C81*M81 -> 0 | P81: =L81*M81 -> 0
A82: =Autovalutazione!A84 -> 2.1.2.2.h | B82: =Autovalutazione!C84 -> Altro? Specificare | C82: =IF(ISBLANK(Autovalutazione!D84),0,1) -> 0 | D82: =IF(AND(Autovalutazione!D84="",Autovalutazione!E84=""),"*","") -> * | E82: =IF(ISBLANK(Autovalutazione!F84),"",Autovalutazione!F84) | M82: 0 | O82: =C82*M82 -> 0 | P82: =L82*M82 -> 0
A83: =Autovalutazione!A85 -> 2.1.2.3.a | B83: =Autovalutazione!C85 -> I compiti, le competenze e le responsabilità (diritti e doveri) in materia di sicurezza e salute sono parte integrante dei seguenti documenti? Descrizioni dei posti di lavoro? | C83: =IF(ISBLANK(Autovalutazione!D85),0,1) -> 0 | D83: =IF(AND(Autovalutazione!D85="",Autovalutazione!E85=""),"*","") -> * | E83: =IF(ISBLANK(Autovalutazione!F85),"",Autovalutazione!F85) | M83: 5 | O83: =C83*M83 -> 0 | P83: =L83*M83 -> 0
A84: =Autovalutazione!A86 -> 2.1.2.3.b | B84: =Autovalutazione!C86 -> Mansionari? | C84: =IF(ISBLANK(Autovalutazione!D86),0,1) -> 0 | D84: =IF(AND(Autovalutazione!D86="",Autovalutazione!E86=""),"*","") -> * | E84: =IF(ISBLANK(Autovalutazione!F86),"",Autovalutazione!F86) | M84: 1 | O84: =C84*M84 -> 0 | P84: =L84*M84 -> 0
A85: =Autovalutazione!A87 -> 2.1.2.3.c | B85: =Autovalutazione!C87 -> Diagrammi delle funzioni? | C85: =IF(ISBLANK(Autovalutazione!D87),0,1) -> 0 | D85: =IF(AND(Autovalutazione!D87="",Autovalutazione!E87=""),"*","") -> * | E85: =IF(ISBLANK(Autovalutazione!F87),"",Autovalutazione!F87) | M85: 0 | O85: =C85*M85 -> 0 | P85: =L85*M85 -> 0
... A90: =Autovalutazione!A92 -> 2.1.2.3.h | B90: =Autovalutazione!C92 -> Altri documenti organizzativi?Specificare | C90: =IF(ISBLANK(Autovalutazione!D92),0,1) -> 0 | D90: =IF(AND(Autovalutazione!D92="",Autovalutazione!E92=""),"*","") -> * | E90: =IF(ISBLANK(Autovalutazione!F92),"",Autovalutazione!F92) | M90: 0 | O90: =C90*M90 -> 0 | P90: =L90*M90 -> 0
A91: =Autovalutazione!A93 -> 2.1.3. | B91: =Autovalutazione!C93 -> Pianificazione e organizzazione del lavoro | C91: =O91/N91 -> 0 | D91: =IF(ISBLANK(Autovalutazione!E93),"",Autovalutazione!E93) | E91: =IF(ISBLANK(Autovalutazione!F93),"",Autovalutazione!F93) | L91: =P91/N91 -> 0 | M91: 2 | N91: =SUM(M92:M102) -> 17 | O91: =SUM(O92:O102) -> 0 | P91: =SUM(P92:P102) -> 0 | Q91: =O91/$N91*$M91 -> 0 | R91: =P91/$N91*$M91 -> 0
A92: =Autovalutazione!A94 -> 2.1.3.1.a | B92: =Autovalutazione!C94 -> Chi svolge la pianificazione, il calcolo, l'organizzazione delle mansioni? Indicare tra i soggetti sotto indicati: superiori di linea? | C92: =IF(ISBLANK(Autovalutazione!D94),0,1) -> 0 | D92: =IF(AND(Autovalutazione!D94="",Autovalutazione!E94=""),"*","") -> * | E92: =IF(ISBLANK(Autovalutazione!F94),"",Autovalutazione!F94) | M92: 3 | O92: =C92*M92 -> 0 | P92: =L92*M92 -> 0
A93: =Autovalutazione!A95 -> 2.1.3.1.b | B93: =Autovalutazione!C95 -> team di progetto? | C93: =IF(ISBLANK(Autovalutazione!D95),0,1) -> 0 | D93: =IF(AND(Autovalutazione!D95="",Autovalutazione!E95=""),"*","") -> * | E93: =IF(ISBLANK(Autovalutazione!F95),"",Autovalutazione!F95) | M93: 0 | O93: =C93*M93 -> 0 | P93: =L93*M93 -> 0
A94: =Autovalutazione!A96 -> 2.1.3.1.c | B94: =Autovalutazione!C96 -> unità organizzativa creata ad hoc (preparazione dei lavori) | C94: =IF(ISBLANK(Autovalutazione!D96),0,1) -> 0 | D94: =IF(AND(Autovalutazione!D96="",Autovalutazione!E96=""),"*","") -> * | E94: =IF(ISBLANK(Autovalutazione!F96),"",Autovalutazione!F96) | M94: 0 | O94: =C94*M94 -> 0 | P94: =L94*M94 -> 0
A95: =Autovalutazione!A97 -> 2.1.3.1.d | B95: =Autovalutazione!C97 -> Altri organi / persone? Se sì, quali organi / persone? | C95: =IF(ISBLANK(Autovalutazione!D97),0,1) -> 0 | D95: =IF(AND(Autovalutazione!D97="",Autovalutazione!E97=""),"*","") -> * | E95: =IF(ISBLANK(Autovalutazione!F97),"",Autovalutazione!F97) | M95: 0 | O95: =C95*M95 -> 0 | P95: =L95*M95 -> 0
A96: =Autovalutazione!A98 -> 2.1.3.2. | B96: =Autovalutazione!C98 -> Nella fase di pianificazione, organizzazione, preparazione si tiene conto degli aspetti di sicurezza e tutela della salute? | C96: =IF(ISBLANK(Autovalutazione!D98),0,1) -> 0 | D96: =IF(AND(Autovalutazione!D98="",Autovalutazione!E98=""),"*","") -> * | E96: =IF(ISBLANK(Autovalutazione!F98),"",Autovalutazione!F98) | M96: 5 | O96: =C96*M96 -> 0 | P96: =L96*M96 -> 0
A97: =Autovalutazione!A99 -> 2.1.3.3. | B97: =Autovalutazione!C99 -> Esiste una separazione netta tra la pianificazione, organizzazione e preparazione dei lavori e la loro esecuzione? | C97: =IF(ISBLANK(Autovalutazione!D99),0,1) -> 0 | D97: =IF(AND(Autovalutazione!D99="",Autovalutazione!E99=""),"*","") -> * | E97: =IF(ISBLANK(Autovalutazione!F99),"",Autovalutazione!F99) | M97: 0 | O97: =C97*M97 -> 0 | P97: =L97*M97 -> 0
A98: =Autovalutazione!A100 -> 2.1.3.4. | B98: =Autovalutazione!C100 -> Il livello di esecuzione è coinvolto nella fase di preparazione del lavoro? | C98: =IF(ISBLANK(Autovalutazione!D100),0,1) -> 0 | D98: =IF(AND(Autovalutazione!D100="",Autovalutazione!E100=""),"*","") -> * | E98: =IF(ISBLANK(Autovalutazione!F100),"",Autovalutazione!F100) | M98: 0 | O98: =C98*M98 -> 0 | P98: =L98*M98 -> 0
A99: =Autovalutazione!A101 -> 2.1.3.5. | B99: =Autovalutazione!C101 -> Gli incarichi di lavoro vengono spiegati e discussi? | C99: =IF(ISBLANK(Autovalutazione!D101),0,1) -> 0 | D99: =IF(AND(Autovalutazione!D101="",Autovalutazione!E101=""),"*","") -> * | E99: =IF(ISBLANK(Autovalutazione!F101),"",Autovalutazione!F101) | M99: 3 | O99: =C99*M99 -> 0 | P99: =L99*M99 -> 0
A100: =Autovalutazione!A102 -> 2.1.3.6. | B100: =Autovalutazione!C102 -> La sicurezza e la tutela della salute sono parte integrante degli incarichi? | C100: =IF(ISBLANK(Autovalutazione!D102),0,1) -> 0 | D100: =IF(AND(Autovalutazione!D102="",Autovalutazione!E102=""),"*","") -> * | E100: =IF(ISBLANK(Autovalutazione!F102),"",Autovalutazione!F102) | M100: 3 | O100: =C100*M100 -> 0 | P100: =L100*M100 -> 0
A101: =Autovalutazione!A103 -> 2.1.3.7. | B101: =Autovalutazione!C103 -> Gli incarichi vengono assegnati per iscritto e documentati? | C101: =IF(ISBLANK(Autovalutazione!D103),0,1) -> 0 | D101: =IF(AND(Autovalutazione!D103="",Autovalutazione!E103=""),"*","") -> * | E101: =IF(ISBLANK(Autovalutazione!F103),"",Autovalutazione!F103) | M101: 2 | O101: =C101*M101 -> 0 | P101: =L101*M101 -> 0
A102: =Autovalutazione!A104 -> 2.1.3.8. | B102: =Autovalutazione!C104 -> Le direttive di lavoro in forma scritta riportano indicazioni sulle misure di sicurezza e di tutela della salute? | C102: =IF(ISBLANK(Autovalutazione!D104),0,1) -> 0 | D102: =IF(AND(Autovalutazione!D104="",Autovalutazione!E104=""),"*","") -> * | E102: =IF(ISBLANK(Autovalutazione!F104),"",Autovalutazione!F104) | M102: 1 | O102: =C102*M102 -> 0 | P102: =L102*M102 -> 0
A103: =Autovalutazione!A105 -> 2.1.4. | B103: =Autovalutazione!C105 -> Regolamento aziendale | C103: =O103/N103 -> 0 | D103: =IF(ISBLANK(Autovalutazione!E105),"",Autovalutazione!E105) | E103: =IF(ISBLANK(Autovalutazione!F105),"",Autovalutazione!F105) | L103: =P103/N103 -> 0 | M103: 1 | N103: =MAX(M104:M105) -> 1 | O103: =MAX(O104:O105) -> 0 | P103: =MAX(P104:P105) -> 0 | Q103: =O103/N103*M103 -> 0 | R103: =P103/N103*$M103 -> 0
A104: =Autovalutazione!A106 -> 2.1.4.1. | B104: =Autovalutazione!C106 -> La vostra azienda ha un regolamento obbligatorio ai sensi della Legge sul lavoro? | C104: =IF(ISBLANK(Autovalutazione!D106),0,1) -> 0 | D104: =IF(AND(Autovalutazione!D106="",Autovalutazione!E106=""),"*","") -> * | E104: =IF(ISBLANK(Autovalutazione!F106),"",Autovalutazione!F106) | M104: 1 | O104: =C104*M104 -> 0 | P104: =L104*M104 -> 0
...

Sheet Auswertungen
B2: Legende im Spinnendiagramm:
A3: Erfüllungsgrad | B3: ="Autovalutazione "&Analyse!B1 -> Autovalutazione Muster AG | D3: Valutazione Suva | G3: Delta Suva - Kunde
B4: Berechnung automatisch | C4: Spinnendiagramm überschreibbar | D4: Berechnung automatisch | E4: Spinnendiagramm überschreibbar | G4: Zur Information
A5: =CONCATENATE(Analyse!A4," ",Analyse!B4) -> 1 Principi, obiettivi e strategie | B5: =Analyse!C4 -> 0 | C5: =B5 -> 0 | D5: =Analyse!L4 -> 0 | E5: =D5 -> 0 | G5: =E5-C5 -> 0
A6: =CONCATENATE(Analyse!A64," ",Analyse!B64) -> 2. Organizzazione | B6: =Analyse!C64 -> 0 | C6: =B6 -> 0 | D6: =Analyse!L64 -> 0 | E6: =D6 -> 0 | G6: =E6-C6 -> 0
A7: =CONCATENATE(Analyse!A144," ",Analyse!B144) -> 3. Qualificazione, formazione, comunicazione | B7: =Analyse!C144 -> 0 | C7: =B7 -> 0 | D7: =Analyse!L144 -> 0 | E7: =D7 -> 0 | G7: =E7-C7 -> 0
A8: =CONCATENATE(Analyse!A240," ",Analyse!B240) -> 4. Norme di sicurezza | B8: =Analyse!C240 -> 0.5 | C8: =B8 -> 0.5 | D8: =Analyse!L240 -> 0 | E8: =D8 -> 0 | G8: =E8-C8 -> -0.5
A9: =CONCATENATE(Analyse!A319," ",Analyse!B319) -> 5. Individuazione dei pericoli, valutazione dei rischi | B9: =Analyse!C319 -> 0.034090909 | C9: =B9 -> 0.034090909 | D9: =Analyse!L319 -> 0.034090909 | E9: =D9 -> 0.034090909 | G9: =E9-C9 -> 0
A10: =CONCATENATE(Analyse!A368," ",Analyse!B368) -> 6. Misure | B10: =Analyse!C368 -> 0 | C10: =B10 -> 0 | D10: =Analyse!L368 -> 0 | E10: =D10 -> 0 | G10: =E10-C10 -> 0
A11: =CONCATENATE(Analyse!A392," ",Analyse!B392) -> 7. Organizzazione per i casi di emergenza | B11: =Analyse!C392 -> 0 | C11: =B11 -> 0 | D11: =Analyse!L392 -> 0 | E11: =D11 -> 0 | G11: =E11-C11 -> 0
A12: =CONCATENATE(Analyse!A429," ",Analyse!B429) -> 8. Partecipazione | B12: =Analyse!C429 -> 0 | C12: =B12 -> 0 | D12: =Analyse!L429 -> 0 | E12: =D12 -> 0 | G12: =E12-C12 -> 0
A13: =CONCATENATE(Analyse!A445," ",Analyse!B445) -> 9. Tutela della salute | B13: =Analyse!C445 -> 0.15833333 | C13: =B13 -> 0.15833333 | D13: =Analyse!L445 -> 0.15833333 | E13: =D13 -> 0.15833333 | G13: =E13-C13 -> 0
A14: =CONCATENATE(Analyse!A556," ",Analyse!B556) -> 10. Controllo | B14: =Analyse!C556 -> 0 | C14: =B14 -> 0 | D14: =Analyse!L556 -> 0 | E14: =D14 -> 0 | G14: =E14-C14 -> 0
A15: =CONCATENATE(Analyse!A587," ",Analyse!B587) -> 11. Assenze | B15: =Analyse!C587 -> 0 | C15: =B15 -> 0 | D15: =Analyse!L587 -> 0 | E15: =D15 -> 0 | G15: =E15-C15 -> 0
A16: =CONCATENATE(Analyse!A607," ",Analyse!B607) -> 12 Sicurezza nel tempo libero (parte facoltativa) | B16: =Analyse!C607 -> 0 | C16: =B16 -> 0 | D16: =Analyse!L607 -> 0 | E16: =D16 -> 0 | G16: =E16-C16 -> 0
A17: =CONCATENATE(Analyse!A629," ",Analyse!B629) -> 13 GSA: gestione della salute in azienda (parte facoltativa) | B17: =Analyse!C629 -> 0 | C17: =B17 -> 0 | D17: =Analyse!L629 -> 0 | E17: =D17 -> 0 | G17: =E17-C17 -> 0
A18: =CONCATENATE(Analyse!A657," ",Analyse!B657) -> 14 Ampliamento per l'ISO 45001 (parte facoltativa) | B18: =Analyse!C657 -> 0 | C18: =B18 -> 0 | D18: =Analyse!L657 -> 0 | E18: =D18 -> 0 | G18: =E18-C18 -> 0

Sheet Versionenprotokoll
A1: Versionenprotokoll
A3: Version | B3: Sheet | C3: Änderungen
A4: Version 14 | B4: Selbstbeurteilung Kunde | C4: Französische Übersetzung der Frage 2.3.2.3. korrigiert
A5: Freigabe
A6: 45061
B7: Anleitung | C7: Versionnummer aktualisiert
B8: Selbstbeurteilung Kunde | C8: Versionnummer aktualisiert
A9: Version 13 | B9: verschiedene | C9: Formulierungen in der französischen Version kontrolliert und korrigiert durch Sandrine Casanova.
A10: Freigabe
A11: 45028
B12: Anleitung | C12: Versionnummer aktualisiert
B13: Selbstbeurteilung Kunde | C13: Versionnummer aktualisiert
A14: Version 12 | B14: Selbstbeurteilung Kunde | C14: In Fusszeile des Ausdrucks Versionnummer aktualisiert
A15: Freigabe | B15: Anleitung | C15: Versionnummer aktualisiert
A16: 44841 | B16: Analyse | C16: Spalte D "*" eingefügt zur Visualisierung nicht beantwortet.
B17: Analyse | C17: Spalte C formatiert für Visualisierung Ja / Nein
B18: Selbstbeurteilung Kunde | C18: In 9.9.8 und 9.9.9 Fragen 9.9 und 9.3 aus dem ASA-Systemkontrolle Kategorie 3.1 (EKAS 6074/3.1.d 02.2021) eingefügt.
A20: Version 11 | B20: Selbstbeurteilung Kunde | C20: In Fusszeile des Ausdrucks Versionnummer aktualisiert
A21: Freigabe | B21: Anleitung | C21: Versionnummer aktualisiert
A22: 43712 | B22: Selbstbeurteilung Kunde | C22: Anpassung von OHSAS 18001 auf ISO 45001
B23: Generell | C23: Suva Logo aktualisiert
B24: Analyse | C24: Anpassungen von OHSAS 18001 auf ISO 45001
A25: Version 10 | B25: Selbstbeurteilung Kunde | C25: In Fusszeile des Ausdrucks Versionnummer aktualisiert
A26: Freigabe | B26: Anleitung | C26: Versionnummer aktualisiert
A27: 42913 | B27: Analyse | C27: 2.1.3. Gewicht von 1 auf 2 erhöht
B28: Analyse | C28: 1.1.7. Gewicht von 5 auf 2 reduziert
B29: Analyse | C29: 4.1.3. Gewicht von 3 auf 1 reduziert
B30: Analyse | C30: 3.1. falscher Titel korrigiert (Zellenbezug 149 anstatt 148)
B31: Analyse | C31: 4.2. Gewicht von 1 auf 0 reduziert
B32: Analyse | C32: 4.3. Gewicht von 1 auf 2 erhöht
B33: Spinnendiagramme | C33: Legende "Beurteilung Suva" von D3 in Sheet Auswertungen
A35: Version 09 | B35: Selbstbeurteilung Kunde | C35: In Fusszeile des Ausdrucks Versionnummer aktualisiert
A36: Freigabe | B36: Anleitung | C36: Versionnummer aktualisiert
A37: 42555 | B37: Analyse | C37: Gewicht von Kapitel 9.3. physische Belastungen von 3 auf 0 geändert
B38: Analyse | C38: 9.10. Summierung der eigenen Punkte: Formel auf richtige Spalte korrigiert
B39: Analyse | C39: 4.8. Bewertung für Stichproben eingeführt
B40: Analyse | C40: 4.1.3 Gewicht für Booklet von 5 auf 3 reduziert
B41: Diagramme | C41: Rahmenlinie entfernt
A42: Version 08 | B42: Selbstbeurteilung Kunde | C42: In Fusszeile des Ausdrucks Versionnummer aktualisiert
A43: Freigabe | B43: Anleitung | C43: Versionnummer aktualisiert
A44: 42499 | B44: Analyse | C44: Berechnung der PunkteN und O in Zeile 144 für Kapitel 3 bis Zelle 239 korrigiert
A46: Version 07 | C46: Alle Aenderungen gemäss der deutschen Version bis und mit Version 07 vorgenommen.
A47: Freigabe | B47: Selbstbeurteilung Kunde | C47: In Fusszeile des Ausdrucks Versionnummer aktualisiert
A48: 42492 | B48: Anleitung | C48: Versionnummer aktualisiert
B49: Betriebsspiegel | C49: Fehler in der Nummerierung korrigiert
B50: Analyse | C50: Verdeckte Spalten gelöscht
B51: Analyse | C51: Druckbereich festgelegt
B52: Analyse | C52: Berechnungen der Unterkapitelbewertungen für die verschiedenen Stufen in den Kapiteln 1 und 2 korrigiert
B53: Analyse | C53: Berechnung der Unterkapitelbewertungen an verschiedenen Orten in den Kapitel 3-11 korrigiert
B54: Analyse | C54: Bezug im Kapitel 10.3.2. korrigiert
B55: Analyse | C55: Feldfarbe für ja bei 10.3.1. auch auf grau gesetzt
B56: Spinne ohne FZ, BGM, OHSAS | C56: Kundenname in Legende integriert. Quelle für Legendentitel ist aus Auswertungen C3
B57: Spinne mit FZ, BGM, OHSAS | C57: Kundenname in Legende integriert. Quelle für Legendentitel ist aus Auswertungen C3
B58: Auswertungen | C58: Quelle des Kundenamen für Titel in C3 ist Firmenname im Betriebsspiegel.
B59: Versionenprotokoll | C59: neu erstellt
B60: Selbstbeurteilung Kunde | C60: In Fusszeile des Ausdrucks Versionnummer aktualisiert
B61: Anleitung | C61: Versionnummer ergänzt und aktualisiert
C62: Kapitel Freizeitsicherheit ergänzt
C63: Kapitel BGM ergänzt
C64: Verschiedene Fehler gemäss vbr korrigiert
A65: Versionen | C65: Unkoordinierte Vorabversionen
A66: 00 bis 06
